{"data":[{"url":"https://api.github.com/repos/AtomicGameEngine/AtomicGameEngine/issues/1445","repository_url":"https://api.github.com/repos/AtomicGameEngine/AtomicGameEngine","labels_url":"https://api.github.com/repos/AtomicGameEngine/AtomicGameEngine/issues/1445/labels{/name}","comments_url":"https://api.github.com/repos/AtomicGameEngine/AtomicGameEngine/issues/1445/comments","events_url":"https://api.github.com/repos/AtomicGameEngine/AtomicGameEngine/issues/1445/events","html_url":"https://github.com/AtomicGameEngine/AtomicGameEngine/issues/1445","id":206919997,"number":1445,"title":"[Wiki] Code Editor's Display Settings Linux File preference location","user":{"login":"harentius","id":4300680,"avatar_url":"https://avatars1.githubusercontent.com/u/4300680?v=4","gravatar_id":"","url":"https://api.github.com/users/harentius","html_url":"https://github.com/harentius","followers_url":"https://api.github.com/users/harentius/followers","following_url":"https://api.github.com/users/harentius/following{/other_user}","gists_url":"https://api.github.com/users/harentius/gists{/gist_id}","starred_url":"https://api.github.com/users/harentius/starred{/owner}{/repo}","subscriptions_url":"https://api.github.com/users/harentius/subscriptions","organizations_url":"https://api.github.com/users/harentius/orgs","repos_url":"https://api.github.com/users/harentius/repos","events_url":"https://api.github.com/users/harentius/events{/privacy}","received_events_url":"https://api.github.com/users/harentius/received_events","type":"User","site_admin":false},"labels":[],"state":"open","locked":false,"assignee":null,"assignees":[],"milestone":null,"comments":1,"created_at":"2017-02-10T22:13:23Z","updated_at":"2017-02-16T22:34:23Z","closed_at":null,"author_association":"NONE","body":"Can you please specify location of the preference file for Linux on page \r\n[https://github.com/AtomicGameEngine/AtomicGameEngine/wiki/Changing-the-Code-Editor's-Display-Settings](https://github.com/AtomicGameEngine/AtomicGameEngine/wiki/Changing-the-Code-Editor's-Display-Settings) ?\r\n~/.local/share/AtomicEditor/Preferences/prefs.json","reactions":{"url":"https://api.github.com/repos/AtomicGameEngine/AtomicGameEngine/issues/1445/reactions","total_count":0,"+1":0,"-1":0,"laugh":0,"hooray":0,"confused":0,"heart":0}},{"url":"https://api.github.com/repos/AtomicGameEngine/AtomicGameEngine/issues/1444","repository_url":"https://api.github.com/repos/AtomicGameEngine/AtomicGameEngine","labels_url":"https://api.github.com/repos/AtomicGameEngine/AtomicGameEngine/issues/1444/labels{/name}","comments_url":"https://api.github.com/repos/AtomicGameEngine/AtomicGameEngine/issues/1444/comments","events_url":"https://api.github.com/repos/AtomicGameEngine/AtomicGameEngine/issues/1444/events","html_url":"https://github.com/AtomicGameEngine/AtomicGameEngine/pull/1444","id":206680913,"number":1444,"title":"Add Spin control to Animation Toolbar","user":{"login":"JimMarlowe","id":19511757,"avatar_url":"https://avatars2.githubusercontent.com/u/19511757?v=4","gravatar_id":"","url":"https://api.github.com/users/JimMarlowe","html_url":"https://github.com/JimMarlowe","followers_url":"https://api.github.com/users/JimMarlowe/followers","following_url":"https://api.github.com/users/JimMarlowe/following{/other_user}","gists_url":"https://api.github.com/users/JimMarlowe/gists{/gist_id}","starred_url":"https://api.github.com/users/JimMarlowe/starred{/owner}{/repo}","subscriptions_url":"https://api.github.com/users/JimMarlowe/subscriptions","organizations_url":"https://api.github.com/users/JimMarlowe/orgs","repos_url":"https://api.github.com/users/JimMarlowe/repos","events_url":"https://api.github.com/users/JimMarlowe/events{/privacy}","received_events_url":"https://api.github.com/users/JimMarlowe/received_events","type":"User","site_admin":false},"labels":[],"state":"closed","locked":false,"assignee":null,"assignees":[],"milestone":null,"comments":1,"created_at":"2017-02-10T01:24:03Z","updated_at":"2017-04-07T14:10:25Z","closed_at":"2017-02-13T16:56:47Z","author_association":"COLLABORATOR","pull_request":{"url":"https://api.github.com/repos/AtomicGameEngine/AtomicGameEngine/pulls/1444","html_url":"https://github.com/AtomicGameEngine/AtomicGameEngine/pull/1444","diff_url":"https://github.com/AtomicGameEngine/AtomicGameEngine/pull/1444.diff","patch_url":"https://github.com/AtomicGameEngine/AtomicGameEngine/pull/1444.patch"},"body":"This PR adds a control in the Animation Toolbar to spin the previewed model. Though you can use the Inspector to rotate the model, who's got time for that? The control is a Slider, the leftmost position is off, there are 10 steps, the further right the slider is pushed, the faster the spin. Bonus, This feature also works while animations are playing.\r\n","reactions":{"url":"https://api.github.com/repos/AtomicGameEngine/AtomicGameEngine/issues/1444/reactions","total_count":0,"+1":0,"-1":0,"laugh":0,"hooray":0,"confused":0,"heart":0}},{"url":"https://api.github.com/repos/AtomicGameEngine/AtomicGameEngine/issues/1443","repository_url":"https://api.github.com/repos/AtomicGameEngine/AtomicGameEngine","labels_url":"https://api.github.com/repos/AtomicGameEngine/AtomicGameEngine/issues/1443/labels{/name}","comments_url":"https://api.github.com/repos/AtomicGameEngine/AtomicGameEngine/issues/1443/comments","events_url":"https://api.github.com/repos/AtomicGameEngine/AtomicGameEngine/issues/1443/events","html_url":"https://github.com/AtomicGameEngine/AtomicGameEngine/pull/1443","id":205964334,"number":1443,"title":"Real time theme switching in editor","user":{"login":"JimMarlowe","id":19511757,"avatar_url":"https://avatars2.githubusercontent.com/u/19511757?v=4","gravatar_id":"","url":"https://api.github.com/users/JimMarlowe","html_url":"https://github.com/JimMarlowe","followers_url":"https://api.github.com/users/JimMarlowe/followers","following_url":"https://api.github.com/users/JimMarlowe/following{/other_user}","gists_url":"https://api.github.com/users/JimMarlowe/gists{/gist_id}","starred_url":"https://api.github.com/users/JimMarlowe/starred{/owner}{/repo}","subscriptions_url":"https://api.github.com/users/JimMarlowe/subscriptions","organizations_url":"https://api.github.com/users/JimMarlowe/orgs","repos_url":"https://api.github.com/users/JimMarlowe/repos","events_url":"https://api.github.com/users/JimMarlowe/events{/privacy}","received_events_url":"https://api.github.com/users/JimMarlowe/received_events","type":"User","site_admin":false},"labels":[],"state":"closed","locked":false,"assignee":null,"assignees":[],"milestone":null,"comments":3,"created_at":"2017-02-07T17:47:43Z","updated_at":"2017-04-07T14:10:21Z","closed_at":"2017-02-07T22:51:56Z","author_association":"COLLABORATOR","pull_request":{"url":"https://api.github.com/repos/AtomicGameEngine/AtomicGameEngine/pulls/1443","html_url":"https://github.com/AtomicGameEngine/AtomicGameEngine/pull/1443","diff_url":"https://github.com/AtomicGameEngine/AtomicGameEngine/pull/1443.diff","patch_url":"https://github.com/AtomicGameEngine/AtomicGameEngine/pull/1443.patch"},"body":"Allows switching of light and dark editor and code editor themes using an entries in the Developer menu, Toggle Theme and Toggle Code Editor Theme.\r\nThis changes happen in real time, and are saved in the preferences to the last setting you've selected, so it will come back in that theme.\r\n  There are some minor artifacts when switching between the editor themes, a couple of borders and hilights are not changed for Turbobadger reasons and these return to normal on the next editor invocation. Since swapping themes is probably going to be a infrequent operation, it is tolerable.\r\n","reactions":{"url":"https://api.github.com/repos/AtomicGameEngine/AtomicGameEngine/issues/1443/reactions","total_count":0,"+1":0,"-1":0,"laugh":0,"hooray":0,"confused":0,"heart":0}},{"url":"https://api.github.com/repos/AtomicGameEngine/AtomicGameEngine/issues/1442","repository_url":"https://api.github.com/repos/AtomicGameEngine/AtomicGameEngine","labels_url":"https://api.github.com/repos/AtomicGameEngine/AtomicGameEngine/issues/1442/labels{/name}","comments_url":"https://api.github.com/repos/AtomicGameEngine/AtomicGameEngine/issues/1442/comments","events_url":"https://api.github.com/repos/AtomicGameEngine/AtomicGameEngine/issues/1442/events","html_url":"https://github.com/AtomicGameEngine/AtomicGameEngine/issues/1442","id":205756538,"number":1442,"title":"[Events] Expose Player IPC event handlers to editor","user":{"login":"shaddockh","id":2951562,"avatar_url":"https://avatars3.githubusercontent.com/u/2951562?v=4","gravatar_id":"","url":"https://api.github.com/users/shaddockh","html_url":"https://github.com/shaddockh","followers_url":"https://api.github.com/users/shaddockh/followers","following_url":"https://api.github.com/users/shaddockh/following{/other_user}","gists_url":"https://api.github.com/users/shaddockh/gists{/gist_id}","starred_url":"https://api.github.com/users/shaddockh/starred{/owner}{/repo}","subscriptions_url":"https://api.github.com/users/shaddockh/subscriptions","organizations_url":"https://api.github.com/users/shaddockh/orgs","repos_url":"https://api.github.com/users/shaddockh/repos","events_url":"https://api.github.com/users/shaddockh/events{/privacy}","received_events_url":"https://api.github.com/users/shaddockh/received_events","type":"User","site_admin":false},"labels":[],"state":"open","locked":false,"assignee":null,"assignees":[],"milestone":null,"comments":0,"created_at":"2017-02-07T01:12:10Z","updated_at":"2017-02-07T01:12:10Z","closed_at":null,"author_association":"COLLABORATOR","body":"Currently, the player IPC event names have to reside in ```EditorEvents.ts``` because the ```playerapp`` namespace isn't exposed to the editor.  These events are described as:\r\n```\r\nexport const IPCPlayerExitRequestEventType: Atomic.EventType = \"IPCPlayerExitRequest\";\r\nexport const IPCPlayerWindowChangedEventType: Atomic.EventType = \"IPCPlayerWindowChanged\";\r\nexport const IPCPlayerPauseResumeRequestEventType: Atomic.EventType = \"IPCPlayerPauseResumeRequest\";\r\nexport const IPCPlayerPauseStepRequestEventType: Atomic.EventType = \"IPCPlayerPauseStepRequest\";\r\n```\r\n\r\nIdeally, these should be put back in native so that they can be handled like all the other events.  If we don't want to expose the playerapp namespace to the editor, maybe we can redefine these events in the editor namespace.  Not sure the best way to handle this.","reactions":{"url":"https://api.github.com/repos/AtomicGameEngine/AtomicGameEngine/issues/1442/reactions","total_count":0,"+1":0,"-1":0,"laugh":0,"hooray":0,"confused":0,"heart":0}},{"url":"https://api.github.com/repos/AtomicGameEngine/AtomicGameEngine/issues/1441","repository_url":"https://api.github.com/repos/AtomicGameEngine/AtomicGameEngine","labels_url":"https://api.github.com/repos/AtomicGameEngine/AtomicGameEngine/issues/1441/labels{/name}","comments_url":"https://api.github.com/repos/AtomicGameEngine/AtomicGameEngine/issues/1441/comments","events_url":"https://api.github.com/repos/AtomicGameEngine/AtomicGameEngine/issues/1441/events","html_url":"https://github.com/AtomicGameEngine/AtomicGameEngine/pull/1441","id":205750182,"number":1441,"title":"Programmatically jump to line in editor","user":{"login":"shaddockh","id":2951562,"avatar_url":"https://avatars3.githubusercontent.com/u/2951562?v=4","gravatar_id":"","url":"https://api.github.com/users/shaddockh","html_url":"https://github.com/shaddockh","followers_url":"https://api.github.com/users/shaddockh/followers","following_url":"https://api.github.com/users/shaddockh/following{/other_user}","gists_url":"https://api.github.com/users/shaddockh/gists{/gist_id}","starred_url":"https://api.github.com/users/shaddockh/starred{/owner}{/repo}","subscriptions_url":"https://api.github.com/users/shaddockh/subscriptions","organizations_url":"https://api.github.com/users/shaddockh/orgs","repos_url":"https://api.github.com/users/shaddockh/repos","events_url":"https://api.github.com/users/shaddockh/events{/privacy}","received_events_url":"https://api.github.com/users/shaddockh/received_events","type":"User","site_admin":false},"labels":[],"state":"closed","locked":false,"assignee":null,"assignees":[],"milestone":{"url":"https://api.github.com/repos/AtomicGameEngine/AtomicGameEngine/milestones/4","html_url":"https://github.com/AtomicGameEngine/AtomicGameEngine/milestone/4","labels_url":"https://api.github.com/repos/AtomicGameEngine/AtomicGameEngine/milestones/4/labels","id":2226050,"number":4,"title":"Atomic Build 4","description":"","creator":{"login":"JoshEngebretson","id":376203,"avatar_url":"https://avatars3.githubusercontent.com/u/376203?v=4","gravatar_id":"","url":"https://api.github.com/users/JoshEngebretson","html_url":"https://github.com/JoshEngebretson","followers_url":"https://api.github.com/users/JoshEngebretson/followers","following_url":"https://api.github.com/users/JoshEngebretson/following{/other_user}","gists_url":"https://api.github.com/users/JoshEngebretson/gists{/gist_id}","starred_url":"https://api.github.com/users/JoshEngebretson/starred{/owner}{/repo}","subscriptions_url":"https://api.github.com/users/JoshEngebretson/subscriptions","organizations_url":"https://api.github.com/users/JoshEngebretson/orgs","repos_url":"https://api.github.com/users/JoshEngebretson/repos","events_url":"https://api.github.com/users/JoshEngebretson/events{/privacy}","received_events_url":"https://api.github.com/users/JoshEngebretson/received_events","type":"User","site_admin":false},"open_issues":8,"closed_issues":12,"state":"open","created_at":"2017-01-03T18:50:10Z","updated_at":"2017-03-17T17:45:19Z","due_on":"2017-02-09T08:00:00Z","closed_at":null},"comments":0,"created_at":"2017-02-07T00:31:40Z","updated_at":"2017-02-07T16:38:29Z","closed_at":"2017-02-07T16:38:22Z","author_association":"COLLABORATOR","pull_request":{"url":"https://api.github.com/repos/AtomicGameEngine/AtomicGameEngine/pulls/1441","html_url":"https://github.com/AtomicGameEngine/AtomicGameEngine/pull/1441","diff_url":"https://github.com/AtomicGameEngine/AtomicGameEngine/pull/1441.diff","patch_url":"https://github.com/AtomicGameEngine/AtomicGameEngine/pull/1441.patch"},"body":"This PR wires up the JSResourceEditor::JumpToLineNumber and JumpToToken methods so that the editor can programmatically jump to a line number.  It additionally does the following:\r\n- Can request to load an editor tab passing a file path and also a line number and it will either load up a new editor and jump to the line or switch to it if it was previously loaded and jump to the line\r\n- work on the TypeScript compiler so that the compile results window that pops up is non-modal and magnifying glass icons appear next to each error.  Clicking the magnifying glass will load that file and jump to the line number\r\n\r\n@JoshEngebretson At one point, wasn't there an \"Errors\" or \"Issues\" tab in the editor?  Do you think it would be a good idea to bring something like that back and then expose an API to be able to populate it with bookmarks to editor locations?  Bookmarks could be user set bookmarks, or a TODO parser that populates it, or the TS Compiler errors, or even a log scanner that scans the player log for errors?  If so, maybe that could be a followup issue?","reactions":{"url":"https://api.github.com/repos/AtomicGameEngine/AtomicGameEngine/issues/1441/reactions","total_count":1,"+1":1,"-1":0,"laugh":0,"hooray":0,"confused":0,"heart":0}},{"url":"https://api.github.com/repos/AtomicGameEngine/AtomicGameEngine/issues/1440","repository_url":"https://api.github.com/repos/AtomicGameEngine/AtomicGameEngine","labels_url":"https://api.github.com/repos/AtomicGameEngine/AtomicGameEngine/issues/1440/labels{/name}","comments_url":"https://api.github.com/repos/AtomicGameEngine/AtomicGameEngine/issues/1440/comments","events_url":"https://api.github.com/repos/AtomicGameEngine/AtomicGameEngine/issues/1440/events","html_url":"https://github.com/AtomicGameEngine/AtomicGameEngine/pull/1440","id":205689527,"number":1440,"title":"Updating examples submodule","user":{"login":"JoshEngebretson","id":376203,"avatar_url":"https://avatars3.githubusercontent.com/u/376203?v=4","gravatar_id":"","url":"https://api.github.com/users/JoshEngebretson","html_url":"https://github.com/JoshEngebretson","followers_url":"https://api.github.com/users/JoshEngebretson/followers","following_url":"https://api.github.com/users/JoshEngebretson/following{/other_user}","gists_url":"https://api.github.com/users/JoshEngebretson/gists{/gist_id}","starred_url":"https://api.github.com/users/JoshEngebretson/starred{/owner}{/repo}","subscriptions_url":"https://api.github.com/users/JoshEngebretson/subscriptions","organizations_url":"https://api.github.com/users/JoshEngebretson/orgs","repos_url":"https://api.github.com/users/JoshEngebretson/repos","events_url":"https://api.github.com/users/JoshEngebretson/events{/privacy}","received_events_url":"https://api.github.com/users/JoshEngebretson/received_events","type":"User","site_admin":false},"labels":[],"state":"closed","locked":false,"assignee":null,"assignees":[],"milestone":null,"comments":0,"created_at":"2017-02-06T19:52:15Z","updated_at":"2017-02-06T20:23:55Z","closed_at":"2017-02-06T20:23:55Z","author_association":"CONTRIBUTOR","pull_request":{"url":"https://api.github.com/repos/AtomicGameEngine/AtomicGameEngine/pulls/1440","html_url":"https://github.com/AtomicGameEngine/AtomicGameEngine/pull/1440","diff_url":"https://github.com/AtomicGameEngine/AtomicGameEngine/pull/1440.diff","patch_url":"https://github.com/AtomicGameEngine/AtomicGameEngine/pull/1440.patch"},"body":"","reactions":{"url":"https://api.github.com/repos/AtomicGameEngine/AtomicGameEngine/issues/1440/reactions","total_count":0,"+1":0,"-1":0,"laugh":0,"hooray":0,"confused":0,"heart":0}},{"url":"https://api.github.com/repos/AtomicGameEngine/AtomicGameEngine/issues/1439","repository_url":"https://api.github.com/repos/AtomicGameEngine/AtomicGameEngine","labels_url":"https://api.github.com/repos/AtomicGameEngine/AtomicGameEngine/issues/1439/labels{/name}","comments_url":"https://api.github.com/repos/AtomicGameEngine/AtomicGameEngine/issues/1439/comments","events_url":"https://api.github.com/repos/AtomicGameEngine/AtomicGameEngine/issues/1439/events","html_url":"https://github.com/AtomicGameEngine/AtomicGameEngine/pull/1439","id":205683019,"number":1439,"title":"Register variant map xml name as significant at load time","user":{"login":"JoshEngebretson","id":376203,"avatar_url":"https://avatars3.githubusercontent.com/u/376203?v=4","gravatar_id":"","url":"https://api.github.com/users/JoshEngebretson","html_url":"https://github.com/JoshEngebretson","followers_url":"https://api.github.com/users/JoshEngebretson/followers","following_url":"https://api.github.com/users/JoshEngebretson/following{/other_user}","gists_url":"https://api.github.com/users/JoshEngebretson/gists{/gist_id}","starred_url":"https://api.github.com/users/JoshEngebretson/starred{/owner}{/repo}","subscriptions_url":"https://api.github.com/users/JoshEngebretson/subscriptions","organizations_url":"https://api.github.com/users/JoshEngebretson/orgs","repos_url":"https://api.github.com/users/JoshEngebretson/repos","events_url":"https://api.github.com/users/JoshEngebretson/events{/privacy}","received_events_url":"https://api.github.com/users/JoshEngebretson/received_events","type":"User","site_admin":false},"labels":[],"state":"closed","locked":false,"assignee":null,"assignees":[],"milestone":null,"comments":0,"created_at":"2017-02-06T19:26:52Z","updated_at":"2017-02-06T20:23:38Z","closed_at":"2017-02-06T20:23:38Z","author_association":"CONTRIBUTOR","pull_request":{"url":"https://api.github.com/repos/AtomicGameEngine/AtomicGameEngine/pulls/1439","html_url":"https://github.com/AtomicGameEngine/AtomicGameEngine/pull/1439","diff_url":"https://github.com/AtomicGameEngine/AtomicGameEngine/pull/1439.diff","patch_url":"https://github.com/AtomicGameEngine/AtomicGameEngine/pull/1439.patch"},"body":"","reactions":{"url":"https://api.github.com/repos/AtomicGameEngine/AtomicGameEngine/issues/1439/reactions","total_count":0,"+1":0,"-1":0,"laugh":0,"hooray":0,"confused":0,"heart":0}},{"url":"https://api.github.com/repos/AtomicGameEngine/AtomicGameEngine/issues/1438","repository_url":"https://api.github.com/repos/AtomicGameEngine/AtomicGameEngine","labels_url":"https://api.github.com/repos/AtomicGameEngine/AtomicGameEngine/issues/1438/labels{/name}","comments_url":"https://api.github.com/repos/AtomicGameEngine/AtomicGameEngine/issues/1438/comments","events_url":"https://api.github.com/repos/AtomicGameEngine/AtomicGameEngine/issues/1438/events","html_url":"https://github.com/AtomicGameEngine/AtomicGameEngine/pull/1438","id":205673020,"number":1438,"title":"Fix event handler to use the native wrapper.  ","user":{"login":"shaddockh","id":2951562,"avatar_url":"https://avatars3.githubusercontent.com/u/2951562?v=4","gravatar_id":"","url":"https://api.github.com/users/shaddockh","html_url":"https://github.com/shaddockh","followers_url":"https://api.github.com/users/shaddockh/followers","following_url":"https://api.github.com/users/shaddockh/following{/other_user}","gists_url":"https://api.github.com/users/shaddockh/gists{/gist_id}","starred_url":"https://api.github.com/users/shaddockh/starred{/owner}{/repo}","subscriptions_url":"https://api.github.com/users/shaddockh/subscriptions","organizations_url":"https://api.github.com/users/shaddockh/orgs","repos_url":"https://api.github.com/users/shaddockh/repos","events_url":"https://api.github.com/users/shaddockh/events{/privacy}","received_events_url":"https://api.github.com/users/shaddockh/received_events","type":"User","site_admin":false},"labels":[],"state":"closed","locked":false,"assignee":null,"assignees":[],"milestone":null,"comments":1,"created_at":"2017-02-06T18:44:41Z","updated_at":"2017-02-06T19:20:17Z","closed_at":"2017-02-06T19:20:17Z","author_association":"COLLABORATOR","pull_request":{"url":"https://api.github.com/repos/AtomicGameEngine/AtomicGameEngine/pulls/1438","html_url":"https://github.com/AtomicGameEngine/AtomicGameEngine/pull/1438","diff_url":"https://github.com/AtomicGameEngine/AtomicGameEngine/pull/1438.diff","patch_url":"https://github.com/AtomicGameEngine/AtomicGameEngine/pull/1438.patch"},"body":"The merge pulled out the EditorEvents file that this relied on.","reactions":{"url":"https://api.github.com/repos/AtomicGameEngine/AtomicGameEngine/issues/1438/reactions","total_count":0,"+1":0,"-1":0,"laugh":0,"hooray":0,"confused":0,"heart":0}},{"url":"https://api.github.com/repos/AtomicGameEngine/AtomicGameEngine/issues/1437","repository_url":"https://api.github.com/repos/AtomicGameEngine/AtomicGameEngine","labels_url":"https://api.github.com/repos/AtomicGameEngine/AtomicGameEngine/issues/1437/labels{/name}","comments_url":"https://api.github.com/repos/AtomicGameEngine/AtomicGameEngine/issues/1437/comments","events_url":"https://api.github.com/repos/AtomicGameEngine/AtomicGameEngine/issues/1437/events","html_url":"https://github.com/AtomicGameEngine/AtomicGameEngine/pull/1437","id":205645074,"number":1437,"title":"Add a significant string registry for StringHash, use string instead of hash for variant map XML keys when possible","user":{"login":"JoshEngebretson","id":376203,"avatar_url":"https://avatars3.githubusercontent.com/u/376203?v=4","gravatar_id":"","url":"https://api.github.com/users/JoshEngebretson","html_url":"https://github.com/JoshEngebretson","followers_url":"https://api.github.com/users/JoshEngebretson/followers","following_url":"https://api.github.com/users/JoshEngebretson/following{/other_user}","gists_url":"https://api.github.com/users/JoshEngebretson/gists{/gist_id}","starred_url":"https://api.github.com/users/JoshEngebretson/starred{/owner}{/repo}","subscriptions_url":"https://api.github.com/users/JoshEngebretson/subscriptions","organizations_url":"https://api.github.com/users/JoshEngebretson/orgs","repos_url":"https://api.github.com/users/JoshEngebretson/repos","events_url":"https://api.github.com/users/JoshEngebretson/events{/privacy}","received_events_url":"https://api.github.com/users/JoshEngebretson/received_events","type":"User","site_admin":false},"labels":[],"state":"closed","locked":false,"assignee":null,"assignees":[],"milestone":{"url":"https://api.github.com/repos/AtomicGameEngine/AtomicGameEngine/milestones/4","html_url":"https://github.com/AtomicGameEngine/AtomicGameEngine/milestone/4","labels_url":"https://api.github.com/repos/AtomicGameEngine/AtomicGameEngine/milestones/4/labels","id":2226050,"number":4,"title":"Atomic Build 4","description":"","creator":{"login":"JoshEngebretson","id":376203,"avatar_url":"https://avatars3.githubusercontent.com/u/376203?v=4","gravatar_id":"","url":"https://api.github.com/users/JoshEngebretson","html_url":"https://github.com/JoshEngebretson","followers_url":"https://api.github.com/users/JoshEngebretson/followers","following_url":"https://api.github.com/users/JoshEngebretson/following{/other_user}","gists_url":"https://api.github.com/users/JoshEngebretson/gists{/gist_id}","starred_url":"https://api.github.com/users/JoshEngebretson/starred{/owner}{/repo}","subscriptions_url":"https://api.github.com/users/JoshEngebretson/subscriptions","organizations_url":"https://api.github.com/users/JoshEngebretson/orgs","repos_url":"https://api.github.com/users/JoshEngebretson/repos","events_url":"https://api.github.com/users/JoshEngebretson/events{/privacy}","received_events_url":"https://api.github.com/users/JoshEngebretson/received_events","type":"User","site_admin":false},"open_issues":8,"closed_issues":12,"state":"open","created_at":"2017-01-03T18:50:10Z","updated_at":"2017-03-17T17:45:19Z","due_on":"2017-02-09T08:00:00Z","closed_at":null},"comments":0,"created_at":"2017-02-06T16:54:44Z","updated_at":"2017-02-06T18:11:40Z","closed_at":"2017-02-06T18:11:40Z","author_association":"CONTRIBUTOR","pull_request":{"url":"https://api.github.com/repos/AtomicGameEngine/AtomicGameEngine/pulls/1437","html_url":"https://github.com/AtomicGameEngine/AtomicGameEngine/pull/1437","diff_url":"https://github.com/AtomicGameEngine/AtomicGameEngine/pull/1437.diff","patch_url":"https://github.com/AtomicGameEngine/AtomicGameEngine/pull/1437.patch"},"body":"\r\nThis PR makes script component field values more pleasant in XML, uses field name instead of hash value, resave scene to switch to field names, names and hashes are supported for backwards compatibility.\r\n\r\nCloses #1431","reactions":{"url":"https://api.github.com/repos/AtomicGameEngine/AtomicGameEngine/issues/1437/reactions","total_count":0,"+1":0,"-1":0,"laugh":0,"hooray":0,"confused":0,"heart":0}},{"url":"https://api.github.com/repos/AtomicGameEngine/AtomicGameEngine/issues/1436","repository_url":"https://api.github.com/repos/AtomicGameEngine/AtomicGameEngine","labels_url":"https://api.github.com/repos/AtomicGameEngine/AtomicGameEngine/issues/1436/labels{/name}","comments_url":"https://api.github.com/repos/AtomicGameEngine/AtomicGameEngine/issues/1436/comments","events_url":"https://api.github.com/repos/AtomicGameEngine/AtomicGameEngine/issues/1436/events","html_url":"https://github.com/AtomicGameEngine/AtomicGameEngine/issues/1436","id":205450722,"number":1436,"title":"[Events] Support multiple subscribers with subscribeToEvent","user":{"login":"shaddockh","id":2951562,"avatar_url":"https://avatars3.githubusercontent.com/u/2951562?v=4","gravatar_id":"","url":"https://api.github.com/users/shaddockh","html_url":"https://github.com/shaddockh","followers_url":"https://api.github.com/users/shaddockh/followers","following_url":"https://api.github.com/users/shaddockh/following{/other_user}","gists_url":"https://api.github.com/users/shaddockh/gists{/gist_id}","starred_url":"https://api.github.com/users/shaddockh/starred{/owner}{/repo}","subscriptions_url":"https://api.github.com/users/shaddockh/subscriptions","organizations_url":"https://api.github.com/users/shaddockh/orgs","repos_url":"https://api.github.com/users/shaddockh/repos","events_url":"https://api.github.com/users/shaddockh/events{/privacy}","received_events_url":"https://api.github.com/users/shaddockh/received_events","type":"User","site_admin":false},"labels":[],"state":"closed","locked":false,"assignee":null,"assignees":[],"milestone":null,"comments":1,"created_at":"2017-02-05T20:17:11Z","updated_at":"2017-02-28T17:55:11Z","closed_at":"2017-02-28T17:55:11Z","author_association":"COLLABORATOR","body":"Currently it appears that when using ```subscribeToEvent```, it's only possible to have a single subscriber for each event type associated with a AObject.  \r\n\r\nThis would be more useful if you could have multiple subscribers to an event.  Right now, if you subscribe to an event on an object that already has an existing subscriber, it discards the previous subscription and replaces it with the new one instead of keeping both and then triggering the callback on both when a ```sendEvent``` is fired.","reactions":{"url":"https://api.github.com/repos/AtomicGameEngine/AtomicGameEngine/issues/1436/reactions","total_count":0,"+1":0,"-1":0,"laugh":0,"hooray":0,"confused":0,"heart":0}},{"url":"https://api.github.com/repos/AtomicGameEngine/AtomicGameEngine/issues/1435","repository_url":"https://api.github.com/repos/AtomicGameEngine/AtomicGameEngine","labels_url":"https://api.github.com/repos/AtomicGameEngine/AtomicGameEngine/issues/1435/labels{/name}","comments_url":"https://api.github.com/repos/AtomicGameEngine/AtomicGameEngine/issues/1435/comments","events_url":"https://api.github.com/repos/AtomicGameEngine/AtomicGameEngine/issues/1435/events","html_url":"https://github.com/AtomicGameEngine/AtomicGameEngine/pull/1435","id":205329060,"number":1435,"title":"User and Application settings improvements","user":{"login":"shaddockh","id":2951562,"avatar_url":"https://avatars3.githubusercontent.com/u/2951562?v=4","gravatar_id":"","url":"https://api.github.com/users/shaddockh","html_url":"https://github.com/shaddockh","followers_url":"https://api.github.com/users/shaddockh/followers","following_url":"https://api.github.com/users/shaddockh/following{/other_user}","gists_url":"https://api.github.com/users/shaddockh/gists{/gist_id}","starred_url":"https://api.github.com/users/shaddockh/starred{/owner}{/repo}","subscriptions_url":"https://api.github.com/users/shaddockh/subscriptions","organizations_url":"https://api.github.com/users/shaddockh/orgs","repos_url":"https://api.github.com/users/shaddockh/repos","events_url":"https://api.github.com/users/shaddockh/events{/privacy}","received_events_url":"https://api.github.com/users/shaddockh/received_events","type":"User","site_admin":false},"labels":[],"state":"closed","locked":false,"assignee":null,"assignees":[],"milestone":{"url":"https://api.github.com/repos/AtomicGameEngine/AtomicGameEngine/milestones/4","html_url":"https://github.com/AtomicGameEngine/AtomicGameEngine/milestone/4","labels_url":"https://api.github.com/repos/AtomicGameEngine/AtomicGameEngine/milestones/4/labels","id":2226050,"number":4,"title":"Atomic Build 4","description":"","creator":{"login":"JoshEngebretson","id":376203,"avatar_url":"https://avatars3.githubusercontent.com/u/376203?v=4","gravatar_id":"","url":"https://api.github.com/users/JoshEngebretson","html_url":"https://github.com/JoshEngebretson","followers_url":"https://api.github.com/users/JoshEngebretson/followers","following_url":"https://api.github.com/users/JoshEngebretson/following{/other_user}","gists_url":"https://api.github.com/users/JoshEngebretson/gists{/gist_id}","starred_url":"https://api.github.com/users/JoshEngebretson/starred{/owner}{/repo}","subscriptions_url":"https://api.github.com/users/JoshEngebretson/subscriptions","organizations_url":"https://api.github.com/users/JoshEngebretson/orgs","repos_url":"https://api.github.com/users/JoshEngebretson/repos","events_url":"https://api.github.com/users/JoshEngebretson/events{/privacy}","received_events_url":"https://api.github.com/users/JoshEngebretson/received_events","type":"User","site_admin":false},"open_issues":8,"closed_issues":12,"state":"open","created_at":"2017-01-03T18:50:10Z","updated_at":"2017-03-17T17:45:19Z","due_on":"2017-02-09T08:00:00Z","closed_at":null},"comments":2,"created_at":"2017-02-04T06:57:48Z","updated_at":"2017-02-06T18:44:00Z","closed_at":"2017-02-06T18:05:07Z","author_association":"COLLABORATOR","pull_request":{"url":"https://api.github.com/repos/AtomicGameEngine/AtomicGameEngine/pulls/1435","html_url":"https://github.com/AtomicGameEngine/AtomicGameEngine/pull/1435","diff_url":"https://github.com/AtomicGameEngine/AtomicGameEngine/pull/1435.diff","patch_url":"https://github.com/AtomicGameEngine/AtomicGameEngine/pull/1435.patch"},"body":"This PR enhances the way settings are handled\r\n- Editor level settings can be retrieved and set from editor extensions\r\n- When settings are updated, any open web views will auto-reconfigure the code editor window with any updates.  This allows for changing the code theme on the fly","reactions":{"url":"https://api.github.com/repos/AtomicGameEngine/AtomicGameEngine/issues/1435/reactions","total_count":0,"+1":0,"-1":0,"laugh":0,"hooray":0,"confused":0,"heart":0}},{"url":"https://api.github.com/repos/AtomicGameEngine/AtomicGameEngine/issues/1434","repository_url":"https://api.github.com/repos/AtomicGameEngine/AtomicGameEngine","labels_url":"https://api.github.com/repos/AtomicGameEngine/AtomicGameEngine/issues/1434/labels{/name}","comments_url":"https://api.github.com/repos/AtomicGameEngine/AtomicGameEngine/issues/1434/comments","events_url":"https://api.github.com/repos/AtomicGameEngine/AtomicGameEngine/issues/1434/events","html_url":"https://github.com/AtomicGameEngine/AtomicGameEngine/pull/1434","id":205325065,"number":1434,"title":"Update to Monaco Editor 0.8.1.  Fixes #1392","user":{"login":"shaddockh","id":2951562,"avatar_url":"https://avatars3.githubusercontent.com/u/2951562?v=4","gravatar_id":"","url":"https://api.github.com/users/shaddockh","html_url":"https://github.com/shaddockh","followers_url":"https://api.github.com/users/shaddockh/followers","following_url":"https://api.github.com/users/shaddockh/following{/other_user}","gists_url":"https://api.github.com/users/shaddockh/gists{/gist_id}","starred_url":"https://api.github.com/users/shaddockh/starred{/owner}{/repo}","subscriptions_url":"https://api.github.com/users/shaddockh/subscriptions","organizations_url":"https://api.github.com/users/shaddockh/orgs","repos_url":"https://api.github.com/users/shaddockh/repos","events_url":"https://api.github.com/users/shaddockh/events{/privacy}","received_events_url":"https://api.github.com/users/shaddockh/received_events","type":"User","site_admin":false},"labels":[],"state":"closed","locked":false,"assignee":null,"assignees":[],"milestone":{"url":"https://api.github.com/repos/AtomicGameEngine/AtomicGameEngine/milestones/4","html_url":"https://github.com/AtomicGameEngine/AtomicGameEngine/milestone/4","labels_url":"https://api.github.com/repos/AtomicGameEngine/AtomicGameEngine/milestones/4/labels","id":2226050,"number":4,"title":"Atomic Build 4","description":"","creator":{"login":"JoshEngebretson","id":376203,"avatar_url":"https://avatars3.githubusercontent.com/u/376203?v=4","gravatar_id":"","url":"https://api.github.com/users/JoshEngebretson","html_url":"https://github.com/JoshEngebretson","followers_url":"https://api.github.com/users/JoshEngebretson/followers","following_url":"https://api.github.com/users/JoshEngebretson/following{/other_user}","gists_url":"https://api.github.com/users/JoshEngebretson/gists{/gist_id}","starred_url":"https://api.github.com/users/JoshEngebretson/starred{/owner}{/repo}","subscriptions_url":"https://api.github.com/users/JoshEngebretson/subscriptions","organizations_url":"https://api.github.com/users/JoshEngebretson/orgs","repos_url":"https://api.github.com/users/JoshEngebretson/repos","events_url":"https://api.github.com/users/JoshEngebretson/events{/privacy}","received_events_url":"https://api.github.com/users/JoshEngebretson/received_events","type":"User","site_admin":false},"open_issues":8,"closed_issues":12,"state":"open","created_at":"2017-01-03T18:50:10Z","updated_at":"2017-03-17T17:45:19Z","due_on":"2017-02-09T08:00:00Z","closed_at":null},"comments":1,"created_at":"2017-02-04T05:35:20Z","updated_at":"2017-02-06T18:12:00Z","closed_at":"2017-02-06T17:55:20Z","author_association":"COLLABORATOR","pull_request":{"url":"https://api.github.com/repos/AtomicGameEngine/AtomicGameEngine/pulls/1434","html_url":"https://github.com/AtomicGameEngine/AtomicGameEngine/pull/1434","diff_url":"https://github.com/AtomicGameEngine/AtomicGameEngine/pull/1434.diff","patch_url":"https://github.com/AtomicGameEngine/AtomicGameEngine/pull/1434.patch"},"body":"","reactions":{"url":"https://api.github.com/repos/AtomicGameEngine/AtomicGameEngine/issues/1434/reactions","total_count":1,"+1":1,"-1":0,"laugh":0,"hooray":0,"confused":0,"heart":0}},{"url":"https://api.github.com/repos/AtomicGameEngine/AtomicGameEngine/issues/1433","repository_url":"https://api.github.com/repos/AtomicGameEngine/AtomicGameEngine","labels_url":"https://api.github.com/repos/AtomicGameEngine/AtomicGameEngine/issues/1433/labels{/name}","comments_url":"https://api.github.com/repos/AtomicGameEngine/AtomicGameEngine/issues/1433/comments","events_url":"https://api.github.com/repos/AtomicGameEngine/AtomicGameEngine/issues/1433/events","html_url":"https://github.com/AtomicGameEngine/AtomicGameEngine/pull/1433","id":205303112,"number":1433,"title":"Toggle editor themes","user":{"login":"JimMarlowe","id":19511757,"avatar_url":"https://avatars2.githubusercontent.com/u/19511757?v=4","gravatar_id":"","url":"https://api.github.com/users/JimMarlowe","html_url":"https://github.com/JimMarlowe","followers_url":"https://api.github.com/users/JimMarlowe/followers","following_url":"https://api.github.com/users/JimMarlowe/following{/other_user}","gists_url":"https://api.github.com/users/JimMarlowe/gists{/gist_id}","starred_url":"https://api.github.com/users/JimMarlowe/starred{/owner}{/repo}","subscriptions_url":"https://api.github.com/users/JimMarlowe/subscriptions","organizations_url":"https://api.github.com/users/JimMarlowe/orgs","repos_url":"https://api.github.com/users/JimMarlowe/repos","events_url":"https://api.github.com/users/JimMarlowe/events{/privacy}","received_events_url":"https://api.github.com/users/JimMarlowe/received_events","type":"User","site_admin":false},"labels":[],"state":"closed","locked":false,"assignee":null,"assignees":[],"milestone":null,"comments":6,"created_at":"2017-02-04T00:05:38Z","updated_at":"2017-07-13T15:16:55Z","closed_at":"2017-02-07T15:29:32Z","author_association":"COLLABORATOR","pull_request":{"url":"https://api.github.com/repos/AtomicGameEngine/AtomicGameEngine/pulls/1433","html_url":"https://github.com/AtomicGameEngine/AtomicGameEngine/pull/1433","diff_url":"https://github.com/AtomicGameEngine/AtomicGameEngine/pull/1433.diff","patch_url":"https://github.com/AtomicGameEngine/AtomicGameEngine/pull/1433.patch"},"body":"Allows switching of light and dark editor themes, using an entry in the Developer menu, Toggle Theme.\r\nThis change happens in real time, and is saved in the preferences to the last setting you've selected, so it will come back in that theme.\r\nIt handles 99% of the user interface, there are some minor artifacts when switching between the themes, a couple of borders and hilights are not changed for Turbobadger reasons and these return to normal on the next editor invocation. Since swapping themes is probably going to be a infrequent operation, it is tolerable.\r\nThe codeEditor theme is not changed, and needs some work in order to also change it on the fly.\r\n","reactions":{"url":"https://api.github.com/repos/AtomicGameEngine/AtomicGameEngine/issues/1433/reactions","total_count":0,"+1":0,"-1":0,"laugh":0,"hooray":0,"confused":0,"heart":0}},{"url":"https://api.github.com/repos/AtomicGameEngine/AtomicGameEngine/issues/1432","repository_url":"https://api.github.com/repos/AtomicGameEngine/AtomicGameEngine","labels_url":"https://api.github.com/repos/AtomicGameEngine/AtomicGameEngine/issues/1432/labels{/name}","comments_url":"https://api.github.com/repos/AtomicGameEngine/AtomicGameEngine/issues/1432/comments","events_url":"https://api.github.com/repos/AtomicGameEngine/AtomicGameEngine/issues/1432/events","html_url":"https://github.com/AtomicGameEngine/AtomicGameEngine/pull/1432","id":205272627,"number":1432,"title":"1393 - Update editor to use new event signatures","user":{"login":"shaddockh","id":2951562,"avatar_url":"https://avatars3.githubusercontent.com/u/2951562?v=4","gravatar_id":"","url":"https://api.github.com/users/shaddockh","html_url":"https://github.com/shaddockh","followers_url":"https://api.github.com/users/shaddockh/followers","following_url":"https://api.github.com/users/shaddockh/following{/other_user}","gists_url":"https://api.github.com/users/shaddockh/gists{/gist_id}","starred_url":"https://api.github.com/users/shaddockh/starred{/owner}{/repo}","subscriptions_url":"https://api.github.com/users/shaddockh/subscriptions","organizations_url":"https://api.github.com/users/shaddockh/orgs","repos_url":"https://api.github.com/users/shaddockh/repos","events_url":"https://api.github.com/users/shaddockh/events{/privacy}","received_events_url":"https://api.github.com/users/shaddockh/received_events","type":"User","site_admin":false},"labels":[],"state":"closed","locked":false,"assignee":null,"assignees":[],"milestone":{"url":"https://api.github.com/repos/AtomicGameEngine/AtomicGameEngine/milestones/4","html_url":"https://github.com/AtomicGameEngine/AtomicGameEngine/milestone/4","labels_url":"https://api.github.com/repos/AtomicGameEngine/AtomicGameEngine/milestones/4/labels","id":2226050,"number":4,"title":"Atomic Build 4","description":"","creator":{"login":"JoshEngebretson","id":376203,"avatar_url":"https://avatars3.githubusercontent.com/u/376203?v=4","gravatar_id":"","url":"https://api.github.com/users/JoshEngebretson","html_url":"https://github.com/JoshEngebretson","followers_url":"https://api.github.com/users/JoshEngebretson/followers","following_url":"https://api.github.com/users/JoshEngebretson/following{/other_user}","gists_url":"https://api.github.com/users/JoshEngebretson/gists{/gist_id}","starred_url":"https://api.github.com/users/JoshEngebretson/starred{/owner}{/repo}","subscriptions_url":"https://api.github.com/users/JoshEngebretson/subscriptions","organizations_url":"https://api.github.com/users/JoshEngebretson/orgs","repos_url":"https://api.github.com/users/JoshEngebretson/repos","events_url":"https://api.github.com/users/JoshEngebretson/events{/privacy}","received_events_url":"https://api.github.com/users/JoshEngebretson/received_events","type":"User","site_admin":false},"open_issues":8,"closed_issues":12,"state":"open","created_at":"2017-01-03T18:50:10Z","updated_at":"2017-03-17T17:45:19Z","due_on":"2017-02-09T08:00:00Z","closed_at":null},"comments":1,"created_at":"2017-02-03T21:22:25Z","updated_at":"2017-02-06T17:44:07Z","closed_at":"2017-02-06T17:44:07Z","author_association":"COLLABORATOR","pull_request":{"url":"https://api.github.com/repos/AtomicGameEngine/AtomicGameEngine/pulls/1432","html_url":"https://github.com/AtomicGameEngine/AtomicGameEngine/pull/1432","diff_url":"https://github.com/AtomicGameEngine/AtomicGameEngine/pull/1432.diff","patch_url":"https://github.com/AtomicGameEngine/AtomicGameEngine/pull/1432.patch"},"body":"This PR ended up being quite a bit larger than I anticipated, but I think it really cleans things up. \r\n\r\n fixes #1424 \r\n fixes #1393 \r\n\r\n The following were changed:\r\n\r\n- All of the calls to ```subscribeToEvent``` were updated to use the new signature:\r\n```\r\nsubscribeToEvent(Atomic.UIWidgetEvent((e)=>{ ... }));\r\nunsubscribeFromEvent(Atomic.UIWidgetEventType);\r\n```\r\n- ```sendEvent``` was updated to accept a meta data object like ```subscribeToEvent``` and updated to use the new signature:\r\n```\r\nsendEvent(Atomic.UIWidgetEventData({ data object }));\r\n```\r\n- New method ```Atomic.scriptEventData``` was created for user defined events\r\n- All editor events defined in ```EditorEvents.ts``` were migrated to native code so that they could be manipulated with the new declarative event handling.\r\n- Identified events that were not being referenced anywhere and removed them\r\n  - E_FINDTEXT\r\n  - E_FINDTEXTCLOSE\r\n  - E_FINDTEXTOPEN\r\n  - E_JAVASCRIPTSAVED\r\n  - E_EDITORPLAYSTOP (E_EDITORPLAYERSTOPPED is used insted)\r\n  - E_PLAYERERROR\r\n  - E_CONSOLEMESSAGE\r\n  - E_PLATFORMCHANGE\r\n  - E_CURLCOMPLETE\r\n  - E_EDITORSHUTDOWN\r\n  - E_RESOURCEEDITORCHANGED\r\n\r\n- Modified the JS parsing to extract out comments from ```ATOMIC_EVENT``` and ```ATOMIC_PARM``` calls so that they can be emitted into the ```.d.ts``` file and picked up by TSDoc\r\n  - comment needs to be a single line comment on the line above the ```ATOMIC_EVENT``` or after the param type on the ```ATOMIC_PARM```\r\n- Added some documentation to the events...more needed though.\r\n- Cleaned up events that were not sending the right params or were sending params when there were none identified for that event\r\n- Removed the old style ENUMS from the ```d.ts```.  They are still in the engine so existing JS doesn't break, but TS will display errors until the usage is mapped to the new enums\r\n- Updated all enum references in the editor to use the new style enums","reactions":{"url":"https://api.github.com/repos/AtomicGameEngine/AtomicGameEngine/issues/1432/reactions","total_count":0,"+1":0,"-1":0,"laugh":0,"hooray":0,"confused":0,"heart":0}},{"url":"https://api.github.com/repos/AtomicGameEngine/AtomicGameEngine/issues/1431","repository_url":"https://api.github.com/repos/AtomicGameEngine/AtomicGameEngine","labels_url":"https://api.github.com/repos/AtomicGameEngine/AtomicGameEngine/issues/1431/labels{/name}","comments_url":"https://api.github.com/repos/AtomicGameEngine/AtomicGameEngine/issues/1431/comments","events_url":"https://api.github.com/repos/AtomicGameEngine/AtomicGameEngine/issues/1431/events","html_url":"https://github.com/AtomicGameEngine/AtomicGameEngine/issues/1431","id":204818189,"number":1431,"title":"[C#] Change CSComponent's FieldValues to use the field name instead of the hash of that name","user":{"login":"mattbenic","id":278871,"avatar_url":"https://avatars1.githubusercontent.com/u/278871?v=4","gravatar_id":"","url":"https://api.github.com/users/mattbenic","html_url":"https://github.com/mattbenic","followers_url":"https://api.github.com/users/mattbenic/followers","following_url":"https://api.github.com/users/mattbenic/following{/other_user}","gists_url":"https://api.github.com/users/mattbenic/gists{/gist_id}","starred_url":"https://api.github.com/users/mattbenic/starred{/owner}{/repo}","subscriptions_url":"https://api.github.com/users/mattbenic/subscriptions","organizations_url":"https://api.github.com/users/mattbenic/orgs","repos_url":"https://api.github.com/users/mattbenic/repos","events_url":"https://api.github.com/users/mattbenic/events{/privacy}","received_events_url":"https://api.github.com/users/mattbenic/received_events","type":"User","site_admin":false},"labels":[],"state":"closed","locked":false,"assignee":{"login":"JoshEngebretson","id":376203,"avatar_url":"https://avatars3.githubusercontent.com/u/376203?v=4","gravatar_id":"","url":"https://api.github.com/users/JoshEngebretson","html_url":"https://github.com/JoshEngebretson","followers_url":"https://api.github.com/users/JoshEngebretson/followers","following_url":"https://api.github.com/users/JoshEngebretson/following{/other_user}","gists_url":"https://api.github.com/users/JoshEngebretson/gists{/gist_id}","starred_url":"https://api.github.com/users/JoshEngebretson/starred{/owner}{/repo}","subscriptions_url":"https://api.github.com/users/JoshEngebretson/subscriptions","organizations_url":"https://api.github.com/users/JoshEngebretson/orgs","repos_url":"https://api.github.com/users/JoshEngebretson/repos","events_url":"https://api.github.com/users/JoshEngebretson/events{/privacy}","received_events_url":"https://api.github.com/users/JoshEngebretson/received_events","type":"User","site_admin":false},"assignees":[{"login":"JoshEngebretson","id":376203,"avatar_url":"https://avatars3.githubusercontent.com/u/376203?v=4","gravatar_id":"","url":"https://api.github.com/users/JoshEngebretson","html_url":"https://github.com/JoshEngebretson","followers_url":"https://api.github.com/users/JoshEngebretson/followers","following_url":"https://api.github.com/users/JoshEngebretson/following{/other_user}","gists_url":"https://api.github.com/users/JoshEngebretson/gists{/gist_id}","starred_url":"https://api.github.com/users/JoshEngebretson/starred{/owner}{/repo}","subscriptions_url":"https://api.github.com/users/JoshEngebretson/subscriptions","organizations_url":"https://api.github.com/users/JoshEngebretson/orgs","repos_url":"https://api.github.com/users/JoshEngebretson/repos","events_url":"https://api.github.com/users/JoshEngebretson/events{/privacy}","received_events_url":"https://api.github.com/users/JoshEngebretson/received_events","type":"User","site_admin":false}],"milestone":{"url":"https://api.github.com/repos/AtomicGameEngine/AtomicGameEngine/milestones/4","html_url":"https://github.com/AtomicGameEngine/AtomicGameEngine/milestone/4","labels_url":"https://api.github.com/repos/AtomicGameEngine/AtomicGameEngine/milestones/4/labels","id":2226050,"number":4,"title":"Atomic Build 4","description":"","creator":{"login":"JoshEngebretson","id":376203,"avatar_url":"https://avatars3.githubusercontent.com/u/376203?v=4","gravatar_id":"","url":"https://api.github.com/users/JoshEngebretson","html_url":"https://github.com/JoshEngebretson","followers_url":"https://api.github.com/users/JoshEngebretson/followers","following_url":"https://api.github.com/users/JoshEngebretson/following{/other_user}","gists_url":"https://api.github.com/users/JoshEngebretson/gists{/gist_id}","starred_url":"https://api.github.com/users/JoshEngebretson/starred{/owner}{/repo}","subscriptions_url":"https://api.github.com/users/JoshEngebretson/subscriptions","organizations_url":"https://api.github.com/users/JoshEngebretson/orgs","repos_url":"https://api.github.com/users/JoshEngebretson/repos","events_url":"https://api.github.com/users/JoshEngebretson/events{/privacy}","received_events_url":"https://api.github.com/users/JoshEngebretson/received_events","type":"User","site_admin":false},"open_issues":8,"closed_issues":12,"state":"open","created_at":"2017-01-03T18:50:10Z","updated_at":"2017-03-17T17:45:19Z","due_on":"2017-02-09T08:00:00Z","closed_at":null},"comments":3,"created_at":"2017-02-02T09:15:31Z","updated_at":"2017-02-07T05:34:31Z","closed_at":"2017-02-06T18:11:40Z","author_association":"COLLABORATOR","body":"Currently the fieldvalues in CSComponent use the hash of a field's name to identify the field. This makes it much harder to work directly within the scene or prefab text when not working in the editor. This it also relevant when doing diffs between scenes or prefabs and trying to make sense of those changes. \r\n\r\nThis should be made backwards compatible by supporting _reading_ hashes or names, but _always writing_ names.","reactions":{"url":"https://api.github.com/repos/AtomicGameEngine/AtomicGameEngine/issues/1431/reactions","total_count":0,"+1":0,"-1":0,"laugh":0,"hooray":0,"confused":0,"heart":0}},{"url":"https://api.github.com/repos/AtomicGameEngine/AtomicGameEngine/issues/1430","repository_url":"https://api.github.com/repos/AtomicGameEngine/AtomicGameEngine","labels_url":"https://api.github.com/repos/AtomicGameEngine/AtomicGameEngine/issues/1430/labels{/name}","comments_url":"https://api.github.com/repos/AtomicGameEngine/AtomicGameEngine/issues/1430/comments","events_url":"https://api.github.com/repos/AtomicGameEngine/AtomicGameEngine/issues/1430/events","html_url":"https://github.com/AtomicGameEngine/AtomicGameEngine/pull/1430","id":204814028,"number":1430,"title":"Created a case for UInt types when setting values on CSComponents","user":{"login":"raheelx","id":16516288,"avatar_url":"https://avatars1.githubusercontent.com/u/16516288?v=4","gravatar_id":"","url":"https://api.github.com/users/raheelx","html_url":"https://github.com/raheelx","followers_url":"https://api.github.com/users/raheelx/followers","following_url":"https://api.github.com/users/raheelx/following{/other_user}","gists_url":"https://api.github.com/users/raheelx/gists{/gist_id}","starred_url":"https://api.github.com/users/raheelx/starred{/owner}{/repo}","subscriptions_url":"https://api.github.com/users/raheelx/subscriptions","organizations_url":"https://api.github.com/users/raheelx/orgs","repos_url":"https://api.github.com/users/raheelx/repos","events_url":"https://api.github.com/users/raheelx/events{/privacy}","received_events_url":"https://api.github.com/users/raheelx/received_events","type":"User","site_admin":false},"labels":[],"state":"closed","locked":false,"assignee":null,"assignees":[],"milestone":{"url":"https://api.github.com/repos/AtomicGameEngine/AtomicGameEngine/milestones/4","html_url":"https://github.com/AtomicGameEngine/AtomicGameEngine/milestone/4","labels_url":"https://api.github.com/repos/AtomicGameEngine/AtomicGameEngine/milestones/4/labels","id":2226050,"number":4,"title":"Atomic Build 4","description":"","creator":{"login":"JoshEngebretson","id":376203,"avatar_url":"https://avatars3.githubusercontent.com/u/376203?v=4","gravatar_id":"","url":"https://api.github.com/users/JoshEngebretson","html_url":"https://github.com/JoshEngebretson","followers_url":"https://api.github.com/users/JoshEngebretson/followers","following_url":"https://api.github.com/users/JoshEngebretson/following{/other_user}","gists_url":"https://api.github.com/users/JoshEngebretson/gists{/gist_id}","starred_url":"https://api.github.com/users/JoshEngebretson/starred{/owner}{/repo}","subscriptions_url":"https://api.github.com/users/JoshEngebretson/subscriptions","organizations_url":"https://api.github.com/users/JoshEngebretson/orgs","repos_url":"https://api.github.com/users/JoshEngebretson/repos","events_url":"https://api.github.com/users/JoshEngebretson/events{/privacy}","received_events_url":"https://api.github.com/users/JoshEngebretson/received_events","type":"User","site_admin":false},"open_issues":8,"closed_issues":12,"state":"open","created_at":"2017-01-03T18:50:10Z","updated_at":"2017-03-17T17:45:19Z","due_on":"2017-02-09T08:00:00Z","closed_at":null},"comments":1,"created_at":"2017-02-02T08:52:57Z","updated_at":"2017-02-06T18:12:12Z","closed_at":"2017-02-03T12:49:54Z","author_association":"CONTRIBUTOR","pull_request":{"url":"https://api.github.com/repos/AtomicGameEngine/AtomicGameEngine/pulls/1430","html_url":"https://github.com/AtomicGameEngine/AtomicGameEngine/pull/1430","diff_url":"https://github.com/AtomicGameEngine/AtomicGameEngine/pull/1430.diff","patch_url":"https://github.com/AtomicGameEngine/AtomicGameEngine/pull/1430.patch"},"body":"Hi @JoshEngebretson \r\n\r\ni added a case for uints when setting values to fields on a CSComponent. \r\n\r\n- Raheel ","reactions":{"url":"https://api.github.com/repos/AtomicGameEngine/AtomicGameEngine/issues/1430/reactions","total_count":0,"+1":0,"-1":0,"laugh":0,"hooray":0,"confused":0,"heart":0}},{"url":"https://api.github.com/repos/AtomicGameEngine/AtomicGameEngine/issues/1429","repository_url":"https://api.github.com/repos/AtomicGameEngine/AtomicGameEngine","labels_url":"https://api.github.com/repos/AtomicGameEngine/AtomicGameEngine/issues/1429/labels{/name}","comments_url":"https://api.github.com/repos/AtomicGameEngine/AtomicGameEngine/issues/1429/comments","events_url":"https://api.github.com/repos/AtomicGameEngine/AtomicGameEngine/issues/1429/events","html_url":"https://github.com/AtomicGameEngine/AtomicGameEngine/issues/1429","id":204137608,"number":1429,"title":"Incorrect FBX import","user":{"login":"nem0","id":153526,"avatar_url":"https://avatars1.githubusercontent.com/u/153526?v=4","gravatar_id":"","url":"https://api.github.com/users/nem0","html_url":"https://github.com/nem0","followers_url":"https://api.github.com/users/nem0/followers","following_url":"https://api.github.com/users/nem0/following{/other_user}","gists_url":"https://api.github.com/users/nem0/gists{/gist_id}","starred_url":"https://api.github.com/users/nem0/starred{/owner}{/repo}","subscriptions_url":"https://api.github.com/users/nem0/subscriptions","organizations_url":"https://api.github.com/users/nem0/orgs","repos_url":"https://api.github.com/users/nem0/repos","events_url":"https://api.github.com/users/nem0/events{/privacy}","received_events_url":"https://api.github.com/users/nem0/received_events","type":"User","site_admin":false},"labels":[],"state":"open","locked":false,"assignee":null,"assignees":[],"milestone":null,"comments":5,"created_at":"2017-01-30T21:37:30Z","updated_at":"2017-02-01T09:16:04Z","closed_at":null,"author_association":"NONE","body":"FBX file: [default_pose_char+wep.zip](https://github.com/AtomicGameEngine/AtomicGameEngine/files/740427/default_pose_char.wep.zip)\r\n\r\nAtomic (see \"flying\" scope): \r\n![atomic](https://cloud.githubusercontent.com/assets/153526/22442607/4a6dc1f2-e73c-11e6-819e-02a9ee069b96.png)\r\n\r\nBlender: \r\n![blender](https://cloud.githubusercontent.com/assets/153526/22442722/95bd051e-e73c-11e6-95f7-0902279b82c8.png)\r\n","reactions":{"url":"https://api.github.com/repos/AtomicGameEngine/AtomicGameEngine/issues/1429/reactions","total_count":0,"+1":0,"-1":0,"laugh":0,"hooray":0,"confused":0,"heart":0}},{"url":"https://api.github.com/repos/AtomicGameEngine/AtomicGameEngine/issues/1428","repository_url":"https://api.github.com/repos/AtomicGameEngine/AtomicGameEngine","labels_url":"https://api.github.com/repos/AtomicGameEngine/AtomicGameEngine/issues/1428/labels{/name}","comments_url":"https://api.github.com/repos/AtomicGameEngine/AtomicGameEngine/issues/1428/comments","events_url":"https://api.github.com/repos/AtomicGameEngine/AtomicGameEngine/issues/1428/events","html_url":"https://github.com/AtomicGameEngine/AtomicGameEngine/issues/1428","id":204046316,"number":1428,"title":"[Script] Generate getter properties for \"Is\" methods","user":{"login":"JoshEngebretson","id":376203,"avatar_url":"https://avatars3.githubusercontent.com/u/376203?v=4","gravatar_id":"","url":"https://api.github.com/users/JoshEngebretson","html_url":"https://github.com/JoshEngebretson","followers_url":"https://api.github.com/users/JoshEngebretson/followers","following_url":"https://api.github.com/users/JoshEngebretson/following{/other_user}","gists_url":"https://api.github.com/users/JoshEngebretson/gists{/gist_id}","starred_url":"https://api.github.com/users/JoshEngebretson/starred{/owner}{/repo}","subscriptions_url":"https://api.github.com/users/JoshEngebretson/subscriptions","organizations_url":"https://api.github.com/users/JoshEngebretson/orgs","repos_url":"https://api.github.com/users/JoshEngebretson/repos","events_url":"https://api.github.com/users/JoshEngebretson/events{/privacy}","received_events_url":"https://api.github.com/users/JoshEngebretson/received_events","type":"User","site_admin":false},"labels":[],"state":"open","locked":false,"assignee":null,"assignees":[],"milestone":{"url":"https://api.github.com/repos/AtomicGameEngine/AtomicGameEngine/milestones/5","html_url":"https://github.com/AtomicGameEngine/AtomicGameEngine/milestone/5","labels_url":"https://api.github.com/repos/AtomicGameEngine/AtomicGameEngine/milestones/5/labels","id":2242346,"number":5,"title":"Issue Staging","description":"A staging area for milestones, while we work through the backlog","creator":{"login":"JoshEngebretson","id":376203,"avatar_url":"https://avatars3.githubusercontent.com/u/376203?v=4","gravatar_id":"","url":"https://api.github.com/users/JoshEngebretson","html_url":"https://github.com/JoshEngebretson","followers_url":"https://api.github.com/users/JoshEngebretson/followers","following_url":"https://api.github.com/users/JoshEngebretson/following{/other_user}","gists_url":"https://api.github.com/users/JoshEngebretson/gists{/gist_id}","starred_url":"https://api.github.com/users/JoshEngebretson/starred{/owner}{/repo}","subscriptions_url":"https://api.github.com/users/JoshEngebretson/subscriptions","organizations_url":"https://api.github.com/users/JoshEngebretson/orgs","repos_url":"https://api.github.com/users/JoshEngebretson/repos","events_url":"https://api.github.com/users/JoshEngebretson/events{/privacy}","received_events_url":"https://api.github.com/users/JoshEngebretson/received_events","type":"User","site_admin":false},"open_issues":70,"closed_issues":3,"state":"open","created_at":"2017-01-11T00:50:23Z","updated_at":"2017-07-07T18:59:07Z","due_on":"2017-12-31T08:00:00Z","closed_at":null},"comments":0,"created_at":"2017-01-30T15:45:25Z","updated_at":"2017-01-30T15:45:25Z","closed_at":null,"author_association":"CONTRIBUTOR","body":"There are inconsistencies with Is/Get method names for C++ getter methods, for example:\r\n\r\nhttps://github.com/AtomicGameEngine/AtomicGameEngine/blob/498e42fcc2ec8f6dbc1a3a78ea0345c1d3931b0d/Source/Atomic/Graphics/ParticleEmitter.h#L97\r\n\r\nThese shouldn't be renamed to \"Get\", though the binding tech should know to treat them as property getters in JS/TS/C#","reactions":{"url":"https://api.github.com/repos/AtomicGameEngine/AtomicGameEngine/issues/1428/reactions","total_count":0,"+1":0,"-1":0,"laugh":0,"hooray":0,"confused":0,"heart":0}},{"url":"https://api.github.com/repos/AtomicGameEngine/AtomicGameEngine/issues/1427","repository_url":"https://api.github.com/repos/AtomicGameEngine/AtomicGameEngine","labels_url":"https://api.github.com/repos/AtomicGameEngine/AtomicGameEngine/issues/1427/labels{/name}","comments_url":"https://api.github.com/repos/AtomicGameEngine/AtomicGameEngine/issues/1427/comments","events_url":"https://api.github.com/repos/AtomicGameEngine/AtomicGameEngine/issues/1427/events","html_url":"https://github.com/AtomicGameEngine/AtomicGameEngine/issues/1427","id":203909839,"number":1427,"title":"[Editor] Text clipping in examples / editor UI improvement","user":{"login":"Alan-FGR","id":8399299,"avatar_url":"https://avatars1.githubusercontent.com/u/8399299?v=4","gravatar_id":"","url":"https://api.github.com/users/Alan-FGR","html_url":"https://github.com/Alan-FGR","followers_url":"https://api.github.com/users/Alan-FGR/followers","following_url":"https://api.github.com/users/Alan-FGR/following{/other_user}","gists_url":"https://api.github.com/users/Alan-FGR/gists{/gist_id}","starred_url":"https://api.github.com/users/Alan-FGR/starred{/owner}{/repo}","subscriptions_url":"https://api.github.com/users/Alan-FGR/subscriptions","organizations_url":"https://api.github.com/users/Alan-FGR/orgs","repos_url":"https://api.github.com/users/Alan-FGR/repos","events_url":"https://api.github.com/users/Alan-FGR/events{/privacy}","received_events_url":"https://api.github.com/users/Alan-FGR/received_events","type":"User","site_admin":false},"labels":[{"id":307350266,"url":"https://api.github.com/repos/AtomicGameEngine/AtomicGameEngine/labels/difficulty:%201","name":"difficulty: 1","color":"bfd4f2","default":false},{"id":307350829,"url":"https://api.github.com/repos/AtomicGameEngine/AtomicGameEngine/labels/priority:%20low","name":"priority: low","color":"0052cc","default":false},{"id":170012522,"url":"https://api.github.com/repos/AtomicGameEngine/AtomicGameEngine/labels/type:%20enhancement","name":"type: enhancement","color":"bfdadc","default":false}],"state":"open","locked":false,"assignee":null,"assignees":[],"milestone":null,"comments":0,"created_at":"2017-01-30T00:47:02Z","updated_at":"2017-01-30T00:47:02Z","closed_at":null,"author_association":"COLLABORATOR","body":"Verified on Windows 7, latest build and master.\r\n\r\nText in examples listing are clipped on the 3rd line. A quick fix is to increase the height of the text area a little bit. Ideally make it somewhat responsive, including horizontally because the 3-item columns look ugly on large windows (but I don't know if this latter was reported elsewhere).\r\n\r\n![clipping](https://cloud.githubusercontent.com/assets/8399299/22409600/cfd4de0c-e66a-11e6-8e5f-82797ab89864.PNG)","reactions":{"url":"https://api.github.com/repos/AtomicGameEngine/AtomicGameEngine/issues/1427/reactions","total_count":0,"+1":0,"-1":0,"laugh":0,"hooray":0,"confused":0,"heart":0}},{"url":"https://api.github.com/repos/AtomicGameEngine/AtomicGameEngine/issues/1426","repository_url":"https://api.github.com/repos/AtomicGameEngine/AtomicGameEngine","labels_url":"https://api.github.com/repos/AtomicGameEngine/AtomicGameEngine/issues/1426/labels{/name}","comments_url":"https://api.github.com/repos/AtomicGameEngine/AtomicGameEngine/issues/1426/comments","events_url":"https://api.github.com/repos/AtomicGameEngine/AtomicGameEngine/issues/1426/events","html_url":"https://github.com/AtomicGameEngine/AtomicGameEngine/pull/1426","id":203837954,"number":1426,"title":"Fix for #1425","user":{"login":"shaddockh","id":2951562,"avatar_url":"https://avatars3.githubusercontent.com/u/2951562?v=4","gravatar_id":"","url":"https://api.github.com/users/shaddockh","html_url":"https://github.com/shaddockh","followers_url":"https://api.github.com/users/shaddockh/followers","following_url":"https://api.github.com/users/shaddockh/following{/other_user}","gists_url":"https://api.github.com/users/shaddockh/gists{/gist_id}","starred_url":"https://api.github.com/users/shaddockh/starred{/owner}{/repo}","subscriptions_url":"https://api.github.com/users/shaddockh/subscriptions","organizations_url":"https://api.github.com/users/shaddockh/orgs","repos_url":"https://api.github.com/users/shaddockh/repos","events_url":"https://api.github.com/users/shaddockh/events{/privacy}","received_events_url":"https://api.github.com/users/shaddockh/received_events","type":"User","site_admin":false},"labels":[],"state":"closed","locked":false,"assignee":null,"assignees":[],"milestone":null,"comments":1,"created_at":"2017-01-28T23:01:34Z","updated_at":"2017-01-30T13:07:58Z","closed_at":"2017-01-30T13:07:57Z","author_association":"COLLABORATOR","pull_request":{"url":"https://api.github.com/repos/AtomicGameEngine/AtomicGameEngine/pulls/1426","html_url":"https://github.com/AtomicGameEngine/AtomicGameEngine/pull/1426","diff_url":"https://github.com/AtomicGameEngine/AtomicGameEngine/pull/1426.diff","patch_url":"https://github.com/AtomicGameEngine/AtomicGameEngine/pull/1426.patch"},"body":"@JoshEngebretson, This fixes the issue with the Atom editor displaying the \"js outdated\" error described on the forums.","reactions":{"url":"https://api.github.com/repos/AtomicGameEngine/AtomicGameEngine/issues/1426/reactions","total_count":0,"+1":0,"-1":0,"laugh":0,"hooray":0,"confused":0,"heart":0}},{"url":"https://api.github.com/repos/AtomicGameEngine/AtomicGameEngine/issues/1425","repository_url":"https://api.github.com/repos/AtomicGameEngine/AtomicGameEngine","labels_url":"https://api.github.com/repos/AtomicGameEngine/AtomicGameEngine/issues/1425/labels{/name}","comments_url":"https://api.github.com/repos/AtomicGameEngine/AtomicGameEngine/issues/1425/comments","events_url":"https://api.github.com/repos/AtomicGameEngine/AtomicGameEngine/issues/1425/events","html_url":"https://github.com/AtomicGameEngine/AtomicGameEngine/issues/1425","id":203837198,"number":1425,"title":"[TS Extension] Set \"allowJs\" to false when creating the external tsconfig.json","user":{"login":"shaddockh","id":2951562,"avatar_url":"https://avatars3.githubusercontent.com/u/2951562?v=4","gravatar_id":"","url":"https://api.github.com/users/shaddockh","html_url":"https://github.com/shaddockh","followers_url":"https://api.github.com/users/shaddockh/followers","following_url":"https://api.github.com/users/shaddockh/following{/other_user}","gists_url":"https://api.github.com/users/shaddockh/gists{/gist_id}","starred_url":"https://api.github.com/users/shaddockh/starred{/owner}{/repo}","subscriptions_url":"https://api.github.com/users/shaddockh/subscriptions","organizations_url":"https://api.github.com/users/shaddockh/orgs","repos_url":"https://api.github.com/users/shaddockh/repos","events_url":"https://api.github.com/users/shaddockh/events{/privacy}","received_events_url":"https://api.github.com/users/shaddockh/received_events","type":"User","site_admin":false},"labels":[],"state":"closed","locked":false,"assignee":null,"assignees":[],"milestone":null,"comments":0,"created_at":"2017-01-28T22:49:02Z","updated_at":"2017-01-30T13:07:59Z","closed_at":"2017-01-30T13:07:59Z","author_association":"COLLABORATOR","body":"The setting inside the tsconfig.json for trying to recompile external javascript files should be set to false.  This is an advanced feature and not necessary in most TypeScript projects.\r\n\r\nNeed to set:\r\n```\r\n\"allowJs\": false\r\n```\r\nin the generated tsconfig.","reactions":{"url":"https://api.github.com/repos/AtomicGameEngine/AtomicGameEngine/issues/1425/reactions","total_count":0,"+1":0,"-1":0,"laugh":0,"hooray":0,"confused":0,"heart":0}},{"url":"https://api.github.com/repos/AtomicGameEngine/AtomicGameEngine/issues/1424","repository_url":"https://api.github.com/repos/AtomicGameEngine/AtomicGameEngine","labels_url":"https://api.github.com/repos/AtomicGameEngine/AtomicGameEngine/issues/1424/labels{/name}","comments_url":"https://api.github.com/repos/AtomicGameEngine/AtomicGameEngine/issues/1424/comments","events_url":"https://api.github.com/repos/AtomicGameEngine/AtomicGameEngine/issues/1424/events","html_url":"https://github.com/AtomicGameEngine/AtomicGameEngine/issues/1424","id":203746594,"number":1424,"title":"[Editor] Migrate all the editor internal events to the new event system","user":{"login":"shaddockh","id":2951562,"avatar_url":"https://avatars3.githubusercontent.com/u/2951562?v=4","gravatar_id":"","url":"https://api.github.com/users/shaddockh","html_url":"https://github.com/shaddockh","followers_url":"https://api.github.com/users/shaddockh/followers","following_url":"https://api.github.com/users/shaddockh/following{/other_user}","gists_url":"https://api.github.com/users/shaddockh/gists{/gist_id}","starred_url":"https://api.github.com/users/shaddockh/starred{/owner}{/repo}","subscriptions_url":"https://api.github.com/users/shaddockh/subscriptions","organizations_url":"https://api.github.com/users/shaddockh/orgs","repos_url":"https://api.github.com/users/shaddockh/repos","events_url":"https://api.github.com/users/shaddockh/events{/privacy}","received_events_url":"https://api.github.com/users/shaddockh/received_events","type":"User","site_admin":false},"labels":[],"state":"closed","locked":false,"assignee":{"login":"shaddockh","id":2951562,"avatar_url":"https://avatars3.githubusercontent.com/u/2951562?v=4","gravatar_id":"","url":"https://api.github.com/users/shaddockh","html_url":"https://github.com/shaddockh","followers_url":"https://api.github.com/users/shaddockh/followers","following_url":"https://api.github.com/users/shaddockh/following{/other_user}","gists_url":"https://api.github.com/users/shaddockh/gists{/gist_id}","starred_url":"https://api.github.com/users/shaddockh/starred{/owner}{/repo}","subscriptions_url":"https://api.github.com/users/shaddockh/subscriptions","organizations_url":"https://api.github.com/users/shaddockh/orgs","repos_url":"https://api.github.com/users/shaddockh/repos","events_url":"https://api.github.com/users/shaddockh/events{/privacy}","received_events_url":"https://api.github.com/users/shaddockh/received_events","type":"User","site_admin":false},"assignees":[{"login":"shaddockh","id":2951562,"avatar_url":"https://avatars3.githubusercontent.com/u/2951562?v=4","gravatar_id":"","url":"https://api.github.com/users/shaddockh","html_url":"https://github.com/shaddockh","followers_url":"https://api.github.com/users/shaddockh/followers","following_url":"https://api.github.com/users/shaddockh/following{/other_user}","gists_url":"https://api.github.com/users/shaddockh/gists{/gist_id}","starred_url":"https://api.github.com/users/shaddockh/starred{/owner}{/repo}","subscriptions_url":"https://api.github.com/users/shaddockh/subscriptions","organizations_url":"https://api.github.com/users/shaddockh/orgs","repos_url":"https://api.github.com/users/shaddockh/repos","events_url":"https://api.github.com/users/shaddockh/events{/privacy}","received_events_url":"https://api.github.com/users/shaddockh/received_events","type":"User","site_admin":false}],"milestone":{"url":"https://api.github.com/repos/AtomicGameEngine/AtomicGameEngine/milestones/4","html_url":"https://github.com/AtomicGameEngine/AtomicGameEngine/milestone/4","labels_url":"https://api.github.com/repos/AtomicGameEngine/AtomicGameEngine/milestones/4/labels","id":2226050,"number":4,"title":"Atomic Build 4","description":"","creator":{"login":"JoshEngebretson","id":376203,"avatar_url":"https://avatars3.githubusercontent.com/u/376203?v=4","gravatar_id":"","url":"https://api.github.com/users/JoshEngebretson","html_url":"https://github.com/JoshEngebretson","followers_url":"https://api.github.com/users/JoshEngebretson/followers","following_url":"https://api.github.com/users/JoshEngebretson/following{/other_user}","gists_url":"https://api.github.com/users/JoshEngebretson/gists{/gist_id}","starred_url":"https://api.github.com/users/JoshEngebretson/starred{/owner}{/repo}","subscriptions_url":"https://api.github.com/users/JoshEngebretson/subscriptions","organizations_url":"https://api.github.com/users/JoshEngebretson/orgs","repos_url":"https://api.github.com/users/JoshEngebretson/repos","events_url":"https://api.github.com/users/JoshEngebretson/events{/privacy}","received_events_url":"https://api.github.com/users/JoshEngebretson/received_events","type":"User","site_admin":false},"open_issues":8,"closed_issues":12,"state":"open","created_at":"2017-01-03T18:50:10Z","updated_at":"2017-03-17T17:45:19Z","due_on":"2017-02-09T08:00:00Z","closed_at":null},"comments":4,"created_at":"2017-01-27T21:38:29Z","updated_at":"2017-02-06T17:44:07Z","closed_at":"2017-02-06T17:44:07Z","author_association":"COLLABORATOR","body":"Convert all the events used inside the editor to use the new Atomic Native and Atomic Script events.","reactions":{"url":"https://api.github.com/repos/AtomicGameEngine/AtomicGameEngine/issues/1424/reactions","total_count":0,"+1":0,"-1":0,"laugh":0,"hooray":0,"confused":0,"heart":0}},{"url":"https://api.github.com/repos/AtomicGameEngine/AtomicGameEngine/issues/1423","repository_url":"https://api.github.com/repos/AtomicGameEngine/AtomicGameEngine","labels_url":"https://api.github.com/repos/AtomicGameEngine/AtomicGameEngine/issues/1423/labels{/name}","comments_url":"https://api.github.com/repos/AtomicGameEngine/AtomicGameEngine/issues/1423/comments","events_url":"https://api.github.com/repos/AtomicGameEngine/AtomicGameEngine/issues/1423/events","html_url":"https://github.com/AtomicGameEngine/AtomicGameEngine/issues/1423","id":203734003,"number":1423,"title":"[Linux] Super/Control key detection wrong","user":{"login":"JimMarlowe","id":19511757,"avatar_url":"https://avatars2.githubusercontent.com/u/19511757?v=4","gravatar_id":"","url":"https://api.github.com/users/JimMarlowe","html_url":"https://github.com/JimMarlowe","followers_url":"https://api.github.com/users/JimMarlowe/followers","following_url":"https://api.github.com/users/JimMarlowe/following{/other_user}","gists_url":"https://api.github.com/users/JimMarlowe/gists{/gist_id}","starred_url":"https://api.github.com/users/JimMarlowe/starred{/owner}{/repo}","subscriptions_url":"https://api.github.com/users/JimMarlowe/subscriptions","organizations_url":"https://api.github.com/users/JimMarlowe/orgs","repos_url":"https://api.github.com/users/JimMarlowe/repos","events_url":"https://api.github.com/users/JimMarlowe/events{/privacy}","received_events_url":"https://api.github.com/users/JimMarlowe/received_events","type":"User","site_admin":false},"labels":[],"state":"closed","locked":false,"assignee":null,"assignees":[],"milestone":{"url":"https://api.github.com/repos/AtomicGameEngine/AtomicGameEngine/milestones/5","html_url":"https://github.com/AtomicGameEngine/AtomicGameEngine/milestone/5","labels_url":"https://api.github.com/repos/AtomicGameEngine/AtomicGameEngine/milestones/5/labels","id":2242346,"number":5,"title":"Issue Staging","description":"A staging area for milestones, while we work through the backlog","creator":{"login":"JoshEngebretson","id":376203,"avatar_url":"https://avatars3.githubusercontent.com/u/376203?v=4","gravatar_id":"","url":"https://api.github.com/users/JoshEngebretson","html_url":"https://github.com/JoshEngebretson","followers_url":"https://api.github.com/users/JoshEngebretson/followers","following_url":"https://api.github.com/users/JoshEngebretson/following{/other_user}","gists_url":"https://api.github.com/users/JoshEngebretson/gists{/gist_id}","starred_url":"https://api.github.com/users/JoshEngebretson/starred{/owner}{/repo}","subscriptions_url":"https://api.github.com/users/JoshEngebretson/subscriptions","organizations_url":"https://api.github.com/users/JoshEngebretson/orgs","repos_url":"https://api.github.com/users/JoshEngebretson/repos","events_url":"https://api.github.com/users/JoshEngebretson/events{/privacy}","received_events_url":"https://api.github.com/users/JoshEngebretson/received_events","type":"User","site_admin":false},"open_issues":70,"closed_issues":3,"state":"open","created_at":"2017-01-11T00:50:23Z","updated_at":"2017-07-07T18:59:07Z","due_on":"2017-12-31T08:00:00Z","closed_at":null},"comments":0,"created_at":"2017-01-27T20:36:17Z","updated_at":"2017-07-07T18:59:07Z","closed_at":"2017-07-07T18:59:07Z","author_association":"COLLABORATOR","body":"There are a couple of instances of detecting when the super key on OSX and the Alt Key on Windows is pressed. When compiling for linux, the OSX methodology is being used, it needs to follow the windows way, since linux uses a standard keyboard. ","reactions":{"url":"https://api.github.com/repos/AtomicGameEngine/AtomicGameEngine/issues/1423/reactions","total_count":0,"+1":0,"-1":0,"laugh":0,"hooray":0,"confused":0,"heart":0}},{"url":"https://api.github.com/repos/AtomicGameEngine/AtomicGameEngine/issues/1422","repository_url":"https://api.github.com/repos/AtomicGameEngine/AtomicGameEngine","labels_url":"https://api.github.com/repos/AtomicGameEngine/AtomicGameEngine/issues/1422/labels{/name}","comments_url":"https://api.github.com/repos/AtomicGameEngine/AtomicGameEngine/issues/1422/comments","events_url":"https://api.github.com/repos/AtomicGameEngine/AtomicGameEngine/issues/1422/events","html_url":"https://github.com/AtomicGameEngine/AtomicGameEngine/pull/1422","id":203548046,"number":1422,"title":"Atomic Script Events","user":{"login":"shaddockh","id":2951562,"avatar_url":"https://avatars3.githubusercontent.com/u/2951562?v=4","gravatar_id":"","url":"https://api.github.com/users/shaddockh","html_url":"https://github.com/shaddockh","followers_url":"https://api.github.com/users/shaddockh/followers","following_url":"https://api.github.com/users/shaddockh/following{/other_user}","gists_url":"https://api.github.com/users/shaddockh/gists{/gist_id}","starred_url":"https://api.github.com/users/shaddockh/starred{/owner}{/repo}","subscriptions_url":"https://api.github.com/users/shaddockh/subscriptions","organizations_url":"https://api.github.com/users/shaddockh/orgs","repos_url":"https://api.github.com/users/shaddockh/repos","events_url":"https://api.github.com/users/shaddockh/events{/privacy}","received_events_url":"https://api.github.com/users/shaddockh/received_events","type":"User","site_admin":false},"labels":[],"state":"closed","locked":false,"assignee":null,"assignees":[],"milestone":null,"comments":1,"created_at":"2017-01-27T02:59:18Z","updated_at":"2017-01-27T14:22:11Z","closed_at":"2017-01-27T14:22:11Z","author_association":"COLLABORATOR","pull_request":{"url":"https://api.github.com/repos/AtomicGameEngine/AtomicGameEngine/pulls/1422","html_url":"https://github.com/AtomicGameEngine/AtomicGameEngine/pull/1422","diff_url":"https://github.com/AtomicGameEngine/AtomicGameEngine/pull/1422.diff","patch_url":"https://github.com/AtomicGameEngine/AtomicGameEngine/pull/1422.patch"},"body":"This PR resolved #1302 allowing for a more standard way of defining script events to align with the Native events.  Thanks for the assistance @JoshEngebretson!","reactions":{"url":"https://api.github.com/repos/AtomicGameEngine/AtomicGameEngine/issues/1422/reactions","total_count":0,"+1":0,"-1":0,"laugh":0,"hooray":0,"confused":0,"heart":0}},{"url":"https://api.github.com/repos/AtomicGameEngine/AtomicGameEngine/issues/1421","repository_url":"https://api.github.com/repos/AtomicGameEngine/AtomicGameEngine","labels_url":"https://api.github.com/repos/AtomicGameEngine/AtomicGameEngine/issues/1421/labels{/name}","comments_url":"https://api.github.com/repos/AtomicGameEngine/AtomicGameEngine/issues/1421/comments","events_url":"https://api.github.com/repos/AtomicGameEngine/AtomicGameEngine/issues/1421/events","html_url":"https://github.com/AtomicGameEngine/AtomicGameEngine/issues/1421","id":203508373,"number":1421,"title":"[Editor] Camera continues to move in scene when holding RMB","user":{"login":"LaraEngebretson","id":722928,"avatar_url":"https://avatars0.githubusercontent.com/u/722928?v=4","gravatar_id":"","url":"https://api.github.com/users/LaraEngebretson","html_url":"https://github.com/LaraEngebretson","followers_url":"https://api.github.com/users/LaraEngebretson/followers","following_url":"https://api.github.com/users/LaraEngebretson/following{/other_user}","gists_url":"https://api.github.com/users/LaraEngebretson/gists{/gist_id}","starred_url":"https://api.github.com/users/LaraEngebretson/starred{/owner}{/repo}","subscriptions_url":"https://api.github.com/users/LaraEngebretson/subscriptions","organizations_url":"https://api.github.com/users/LaraEngebretson/orgs","repos_url":"https://api.github.com/users/LaraEngebretson/repos","events_url":"https://api.github.com/users/LaraEngebretson/events{/privacy}","received_events_url":"https://api.github.com/users/LaraEngebretson/received_events","type":"User","site_admin":false},"labels":[],"state":"open","locked":false,"assignee":null,"assignees":[],"milestone":null,"comments":2,"created_at":"2017-01-26T22:29:56Z","updated_at":"2017-02-25T04:30:18Z","closed_at":null,"author_association":"CONTRIBUTOR","body":"This happens on Windows only.\r\n\r\nTo replicate:\r\n* Use RMB to look around the scene\r\n* Stop moving the mouse while continuing to hold RMB ","reactions":{"url":"https://api.github.com/repos/AtomicGameEngine/AtomicGameEngine/issues/1421/reactions","total_count":0,"+1":0,"-1":0,"laugh":0,"hooray":0,"confused":0,"heart":0}},{"url":"https://api.github.com/repos/AtomicGameEngine/AtomicGameEngine/issues/1420","repository_url":"https://api.github.com/repos/AtomicGameEngine/AtomicGameEngine","labels_url":"https://api.github.com/repos/AtomicGameEngine/AtomicGameEngine/issues/1420/labels{/name}","comments_url":"https://api.github.com/repos/AtomicGameEngine/AtomicGameEngine/issues/1420/comments","events_url":"https://api.github.com/repos/AtomicGameEngine/AtomicGameEngine/issues/1420/events","html_url":"https://github.com/AtomicGameEngine/AtomicGameEngine/pull/1420","id":203390619,"number":1420,"title":"Fix ScriptEvent for 1302","user":{"login":"JoshEngebretson","id":376203,"avatar_url":"https://avatars3.githubusercontent.com/u/376203?v=4","gravatar_id":"","url":"https://api.github.com/users/JoshEngebretson","html_url":"https://github.com/JoshEngebretson","followers_url":"https://api.github.com/users/JoshEngebretson/followers","following_url":"https://api.github.com/users/JoshEngebretson/following{/other_user}","gists_url":"https://api.github.com/users/JoshEngebretson/gists{/gist_id}","starred_url":"https://api.github.com/users/JoshEngebretson/starred{/owner}{/repo}","subscriptions_url":"https://api.github.com/users/JoshEngebretson/subscriptions","organizations_url":"https://api.github.com/users/JoshEngebretson/orgs","repos_url":"https://api.github.com/users/JoshEngebretson/repos","events_url":"https://api.github.com/users/JoshEngebretson/events{/privacy}","received_events_url":"https://api.github.com/users/JoshEngebretson/received_events","type":"User","site_admin":false},"labels":[],"state":"closed","locked":false,"assignee":null,"assignees":[],"milestone":null,"comments":1,"created_at":"2017-01-26T14:52:17Z","updated_at":"2017-01-26T16:54:15Z","closed_at":"2017-01-26T16:00:58Z","author_association":"CONTRIBUTOR","pull_request":{"url":"https://api.github.com/repos/AtomicGameEngine/AtomicGameEngine/pulls/1420","html_url":"https://github.com/AtomicGameEngine/AtomicGameEngine/pull/1420","diff_url":"https://github.com/AtomicGameEngine/AtomicGameEngine/pull/1420.diff","patch_url":"https://github.com/AtomicGameEngine/AtomicGameEngine/pull/1420.patch"},"body":"This is a fix for the in progress #1302 branch\r\n\r\nThe parameter count for the native method was incorrect, so the method was never getting called.  \r\n\r\nIt is possible to debug this with the AtomicEditor by passing the --player option, specifying a project, and placing a break point in the method.  \r\n\r\nAtomicEditor --player --project /Users/josh/Documents/AtomicProjects/MyProject\r\n\r\nIf you want variable arguments to a native function btw, specify DUK_VARARGS (then you need to check the stack top for how many args are passed in).  \r\n\r\nI also removed the push of the current function at the top of the method.\r\n\r\nThe code paste now runs!    \r\n\r\n","reactions":{"url":"https://api.github.com/repos/AtomicGameEngine/AtomicGameEngine/issues/1420/reactions","total_count":0,"+1":0,"-1":0,"laugh":0,"hooray":0,"confused":0,"heart":0}},{"url":"https://api.github.com/repos/AtomicGameEngine/AtomicGameEngine/issues/1419","repository_url":"https://api.github.com/repos/AtomicGameEngine/AtomicGameEngine","labels_url":"https://api.github.com/repos/AtomicGameEngine/AtomicGameEngine/issues/1419/labels{/name}","comments_url":"https://api.github.com/repos/AtomicGameEngine/AtomicGameEngine/issues/1419/comments","events_url":"https://api.github.com/repos/AtomicGameEngine/AtomicGameEngine/issues/1419/events","html_url":"https://github.com/AtomicGameEngine/AtomicGameEngine/issues/1419","id":203192856,"number":1419,"title":"[Editor] Allow project assets to be duplicated.","user":{"login":"JimMarlowe","id":19511757,"avatar_url":"https://avatars2.githubusercontent.com/u/19511757?v=4","gravatar_id":"","url":"https://api.github.com/users/JimMarlowe","html_url":"https://github.com/JimMarlowe","followers_url":"https://api.github.com/users/JimMarlowe/followers","following_url":"https://api.github.com/users/JimMarlowe/following{/other_user}","gists_url":"https://api.github.com/users/JimMarlowe/gists{/gist_id}","starred_url":"https://api.github.com/users/JimMarlowe/starred{/owner}{/repo}","subscriptions_url":"https://api.github.com/users/JimMarlowe/subscriptions","organizations_url":"https://api.github.com/users/JimMarlowe/orgs","repos_url":"https://api.github.com/users/JimMarlowe/repos","events_url":"https://api.github.com/users/JimMarlowe/events{/privacy}","received_events_url":"https://api.github.com/users/JimMarlowe/received_events","type":"User","site_admin":false},"labels":[],"state":"open","locked":false,"assignee":null,"assignees":[],"milestone":null,"comments":0,"created_at":"2017-01-25T19:05:18Z","updated_at":"2017-01-25T19:05:18Z","closed_at":null,"author_association":"COLLABORATOR","body":"Much like the duplicate option in the Hierarchy panel, have the same type service in the Project panes for your other assets. You have to go out to the OS to do this presently.\r\nThere should be an auto-naming function for the duplicated item, to avoid name clashes. They can be renamed if the auto-name is not acceptable.\r\nDuplicated files should be made in the same folder as the original (if there are write permissions to do so).","reactions":{"url":"https://api.github.com/repos/AtomicGameEngine/AtomicGameEngine/issues/1419/reactions","total_count":0,"+1":0,"-1":0,"laugh":0,"hooray":0,"confused":0,"heart":0}},{"url":"https://api.github.com/repos/AtomicGameEngine/AtomicGameEngine/issues/1418","repository_url":"https://api.github.com/repos/AtomicGameEngine/AtomicGameEngine","labels_url":"https://api.github.com/repos/AtomicGameEngine/AtomicGameEngine/issues/1418/labels{/name}","comments_url":"https://api.github.com/repos/AtomicGameEngine/AtomicGameEngine/issues/1418/comments","events_url":"https://api.github.com/repos/AtomicGameEngine/AtomicGameEngine/issues/1418/events","html_url":"https://github.com/AtomicGameEngine/AtomicGameEngine/pull/1418","id":203155074,"number":1418,"title":"Close wrapped file when disposing a File.Stream","user":{"login":"mattbenic","id":278871,"avatar_url":"https://avatars1.githubusercontent.com/u/278871?v=4","gravatar_id":"","url":"https://api.github.com/users/mattbenic","html_url":"https://github.com/mattbenic","followers_url":"https://api.github.com/users/mattbenic/followers","following_url":"https://api.github.com/users/mattbenic/following{/other_user}","gists_url":"https://api.github.com/users/mattbenic/gists{/gist_id}","starred_url":"https://api.github.com/users/mattbenic/starred{/owner}{/repo}","subscriptions_url":"https://api.github.com/users/mattbenic/subscriptions","organizations_url":"https://api.github.com/users/mattbenic/orgs","repos_url":"https://api.github.com/users/mattbenic/repos","events_url":"https://api.github.com/users/mattbenic/events{/privacy}","received_events_url":"https://api.github.com/users/mattbenic/received_events","type":"User","site_admin":false},"labels":[],"state":"closed","locked":false,"assignee":null,"assignees":[],"milestone":null,"comments":1,"created_at":"2017-01-25T16:40:52Z","updated_at":"2017-01-25T22:03:02Z","closed_at":"2017-01-25T22:03:02Z","author_association":"COLLABORATOR","pull_request":{"url":"https://api.github.com/repos/AtomicGameEngine/AtomicGameEngine/pulls/1418","html_url":"https://github.com/AtomicGameEngine/AtomicGameEngine/pull/1418","diff_url":"https://github.com/AtomicGameEngine/AtomicGameEngine/pull/1418.diff","patch_url":"https://github.com/AtomicGameEngine/AtomicGameEngine/pull/1418.patch"},"body":"Like it says on the label, fixes (my own damned) rookie mistake","reactions":{"url":"https://api.github.com/repos/AtomicGameEngine/AtomicGameEngine/issues/1418/reactions","total_count":0,"+1":0,"-1":0,"laugh":0,"hooray":0,"confused":0,"heart":0}},{"url":"https://api.github.com/repos/AtomicGameEngine/AtomicGameEngine/issues/1417","repository_url":"https://api.github.com/repos/AtomicGameEngine/AtomicGameEngine","labels_url":"https://api.github.com/repos/AtomicGameEngine/AtomicGameEngine/issues/1417/labels{/name}","comments_url":"https://api.github.com/repos/AtomicGameEngine/AtomicGameEngine/issues/1417/comments","events_url":"https://api.github.com/repos/AtomicGameEngine/AtomicGameEngine/issues/1417/events","html_url":"https://github.com/AtomicGameEngine/AtomicGameEngine/pull/1417","id":203139473,"number":1417,"title":"Fix for Skybox material assignment","user":{"login":"JoshEngebretson","id":376203,"avatar_url":"https://avatars3.githubusercontent.com/u/376203?v=4","gravatar_id":"","url":"https://api.github.com/users/JoshEngebretson","html_url":"https://github.com/JoshEngebretson","followers_url":"https://api.github.com/users/JoshEngebretson/followers","following_url":"https://api.github.com/users/JoshEngebretson/following{/other_user}","gists_url":"https://api.github.com/users/JoshEngebretson/gists{/gist_id}","starred_url":"https://api.github.com/users/JoshEngebretson/starred{/owner}{/repo}","subscriptions_url":"https://api.github.com/users/JoshEngebretson/subscriptions","organizations_url":"https://api.github.com/users/JoshEngebretson/orgs","repos_url":"https://api.github.com/users/JoshEngebretson/repos","events_url":"https://api.github.com/users/JoshEngebretson/events{/privacy}","received_events_url":"https://api.github.com/users/JoshEngebretson/received_events","type":"User","site_admin":false},"labels":[],"state":"closed","locked":false,"assignee":null,"assignees":[],"milestone":{"url":"https://api.github.com/repos/AtomicGameEngine/AtomicGameEngine/milestones/4","html_url":"https://github.com/AtomicGameEngine/AtomicGameEngine/milestone/4","labels_url":"https://api.github.com/repos/AtomicGameEngine/AtomicGameEngine/milestones/4/labels","id":2226050,"number":4,"title":"Atomic Build 4","description":"","creator":{"login":"JoshEngebretson","id":376203,"avatar_url":"https://avatars3.githubusercontent.com/u/376203?v=4","gravatar_id":"","url":"https://api.github.com/users/JoshEngebretson","html_url":"https://github.com/JoshEngebretson","followers_url":"https://api.github.com/users/JoshEngebretson/followers","following_url":"https://api.github.com/users/JoshEngebretson/following{/other_user}","gists_url":"https://api.github.com/users/JoshEngebretson/gists{/gist_id}","starred_url":"https://api.github.com/users/JoshEngebretson/starred{/owner}{/repo}","subscriptions_url":"https://api.github.com/users/JoshEngebretson/subscriptions","organizations_url":"https://api.github.com/users/JoshEngebretson/orgs","repos_url":"https://api.github.com/users/JoshEngebretson/repos","events_url":"https://api.github.com/users/JoshEngebretson/events{/privacy}","received_events_url":"https://api.github.com/users/JoshEngebretson/received_events","type":"User","site_admin":false},"open_issues":8,"closed_issues":12,"state":"open","created_at":"2017-01-03T18:50:10Z","updated_at":"2017-03-17T17:45:19Z","due_on":"2017-02-09T08:00:00Z","closed_at":null},"comments":0,"created_at":"2017-01-25T15:47:08Z","updated_at":"2017-04-09T19:06:56Z","closed_at":"2017-01-25T22:25:05Z","author_association":"CONTRIBUTOR","pull_request":{"url":"https://api.github.com/repos/AtomicGameEngine/AtomicGameEngine/pulls/1417","html_url":"https://github.com/AtomicGameEngine/AtomicGameEngine/pull/1417","diff_url":"https://github.com/AtomicGameEngine/AtomicGameEngine/pull/1417.diff","patch_url":"https://github.com/AtomicGameEngine/AtomicGameEngine/pull/1417.patch"},"body":"","reactions":{"url":"https://api.github.com/repos/AtomicGameEngine/AtomicGameEngine/issues/1417/reactions","total_count":0,"+1":0,"-1":0,"laugh":0,"hooray":0,"confused":0,"heart":0}},{"url":"https://api.github.com/repos/AtomicGameEngine/AtomicGameEngine/issues/1416","repository_url":"https://api.github.com/repos/AtomicGameEngine/AtomicGameEngine","labels_url":"https://api.github.com/repos/AtomicGameEngine/AtomicGameEngine/issues/1416/labels{/name}","comments_url":"https://api.github.com/repos/AtomicGameEngine/AtomicGameEngine/issues/1416/comments","events_url":"https://api.github.com/repos/AtomicGameEngine/AtomicGameEngine/issues/1416/events","html_url":"https://github.com/AtomicGameEngine/AtomicGameEngine/pull/1416","id":202993401,"number":1416,"title":"[Windows] Change graphics backend to use Direct3D 11 by default","user":{"login":"Nyt0x","id":13821052,"avatar_url":"https://avatars1.githubusercontent.com/u/13821052?v=4","gravatar_id":"","url":"https://api.github.com/users/Nyt0x","html_url":"https://github.com/Nyt0x","followers_url":"https://api.github.com/users/Nyt0x/followers","following_url":"https://api.github.com/users/Nyt0x/following{/other_user}","gists_url":"https://api.github.com/users/Nyt0x/gists{/gist_id}","starred_url":"https://api.github.com/users/Nyt0x/starred{/owner}{/repo}","subscriptions_url":"https://api.github.com/users/Nyt0x/subscriptions","organizations_url":"https://api.github.com/users/Nyt0x/orgs","repos_url":"https://api.github.com/users/Nyt0x/repos","events_url":"https://api.github.com/users/Nyt0x/events{/privacy}","received_events_url":"https://api.github.com/users/Nyt0x/received_events","type":"User","site_admin":false},"labels":[],"state":"closed","locked":false,"assignee":null,"assignees":[],"milestone":null,"comments":3,"created_at":"2017-01-25T01:59:45Z","updated_at":"2017-01-25T23:25:28Z","closed_at":"2017-01-25T22:31:56Z","author_association":"NONE","pull_request":{"url":"https://api.github.com/repos/AtomicGameEngine/AtomicGameEngine/pulls/1416","html_url":"https://github.com/AtomicGameEngine/AtomicGameEngine/pull/1416","diff_url":"https://github.com/AtomicGameEngine/AtomicGameEngine/pull/1416.diff","patch_url":"https://github.com/AtomicGameEngine/AtomicGameEngine/pull/1416.patch"},"body":"[Windows] Change graphics backend to use Direct3D 11 by default  issue\r\n#1415\r\n\r\nI think that would be a first step to have d3d11 as the default on windows.","reactions":{"url":"https://api.github.com/repos/AtomicGameEngine/AtomicGameEngine/issues/1416/reactions","total_count":0,"+1":0,"-1":0,"laugh":0,"hooray":0,"confused":0,"heart":0}}],"meta":{"x-ratelimit-limit":"5000","x-ratelimit-remaining":"4410","x-ratelimit-reset":"1507250212","x-github-request-id":"DCA0:572B:DDC48D:1D50226:59D6CD9E","x-github-media-type":"github.squirrel-girl-preview","link":"<https://api.github.com/repositories/29790707/issues?state=all&page=9>; rel=\"next\", <https://api.github.com/repositories/29790707/issues?state=all&page=56>; rel=\"last\", <https://api.github.com/repositories/29790707/issues?state=all&page=1>; rel=\"first\", <https://api.github.com/repositories/29790707/issues?state=all&page=7>; rel=\"prev\"","etag":"\"fbd86515350876f77875684ff9dab020\"","status":"200 OK"}}
